{"0": {"out_links": [[[1, 8192, [], [[[54, "W"], [53, "W"], [52, "W"], [51, "W"]]], 0, 54, 50]]], "input_links": [], "start_time": 0, "visited": 0, "total_needSend": 8192, "end_time": 0, "total_needReceive": 0, "mapto": 54, "exe_time": 6574}, "1": {"out_links": [[[2, 8192, [], [[[50, "N"], [42, "N"], [34, "N"], [26, "N"], [18, "N"], [10, "N"]]], 0, 50, 2]]], "input_links": [], "start_time": 0, "visited": 0, "total_needSend": 8192, "end_time": 0, "total_needReceive": 8192, "mapto": 50, "exe_time": 684}, "2": {"out_links": [[[3, 8192, [], [[[2, "E"], [3, "E"], [4, "E"], [5, "S"], [13, "S"], [21, "S"], [29, "S"]]], 0, 2, 37]]], "input_links": [], "start_time": 0, "visited": 0, "total_needSend": 8192, "end_time": 0, "total_needReceive": 8192, "mapto": 2, "exe_time": 6140}, "3": {"out_links": [[[4, 8192, [], [[[37, "W"], [36, "W"]]], 0, 37, 35]], [[5, 8192, [], [[[37, "S"], [45, "S"], [53, "S"], [61, "W"], [60, "W"]]], 0, 37, 59]], [[6, 8192, [], [[[37, "E"], [38, "S"], [46, "E"]]], 0, 37, 47]], [[7, 8192, [], [[[37, "N"], [29, "N"], [21, "W"], [20, "W"], [19, "W"], [18, "W"], [17, "W"]]], 0, 37, 16]], [[8, 8192, [], [[[37, "E"], [38, "E"], [39, "S"], [47, "S"], [55, "S"]]], 0, 37, 63]], [[9, 8192, [], [[[37, "W"], [36, "W"]]], 0, 37, 35]], [[10, 8192, [], [[[37, "N"], [29, "E"], [30, "E"], [31, "N"], [23, "N"], [15, "N"]]], 0, 37, 7]], [[11, 8192, [], [[[37, "W"], [36, "N"], [28, "N"], [20, "N"], [12, "N"]]], 0, 37, 4]], [[12, 8192, [], [[[37, "E"], [38, "N"]]], 0, 37, 30]], [[13, 8192, [], [[[37, "E"]]], 0, 37, 38]], [[14, 8192, [], [[[37, "S"], [45, "E"]]], 0, 37, 46]]], "input_links": [], "start_time": 0, "visited": 0, "total_needSend": 90112, "end_time": 0, "total_needReceive": 8192, "mapto": 37, "exe_time": 3058}, "4": {"out_links": [[[15, 8192, [], [[[35, "S"], [43, "W"], [42, "S"]]], 0, 35, 50]], [[37, 8192, [], [[[35, "W"], [34, "S"], [42, "W"], [41, "S"], [49, "S"]]], 0, 35, 57]]], "input_links": [], "start_time": 0, "visited": 0, "total_needSend": 16384, "end_time": 0, "total_needReceive": 8192, "mapto": 35, "exe_time": 3883}, "5": {"out_links": [[[16, 8192, [], [[[59, "E"], [60, "N"], [52, "E"], [53, "E"], [54, "E"]]], 0, 59, 55]], [[37, 8192, [], [[[59, "W"], [58, "W"]]], 0, 59, 57]]], "input_links": [], "start_time": 0, "visited": 0, "total_needSend": 16384, "end_time": 0, "total_needReceive": 8192, "mapto": 59, "exe_time": 1660}, "6": {"out_links": [[[17, 8192, [], [[[47, "W"], [46, "W"], [45, "S"], [53, "S"]]], 0, 47, 61]], [[37, 8192, [], [[[47, "S"], [55, "S"], [63, "W"], [62, "W"], [61, "W"], [60, "W"], [59, "W"], [58, "W"]]], 0, 47, 57]]], "input_links": [], "start_time": 0, "visited": 0, "total_needSend": 16384, "end_time": 0, "total_needReceive": 8192, "mapto": 47, "exe_time": 8395}, "7": {"out_links": [[[18, 8192, [], [[[16, "S"], [24, "S"], [32, "S"], [40, "S"], [48, "E"], [49, "E"], [50, "E"], [51, "E"]]], 0, 16, 52]], [[37, 8192, [], [[[16, "E"], [17, "S"], [25, "S"], [33, "S"], [41, "S"], [49, "S"]]], 0, 16, 57]]], "input_links": [], "start_time": 0, "visited": 0, "total_needSend": 16384, "end_time": 0, "total_needReceive": 8192, "mapto": 16, "exe_time": 4876}, "8": {"out_links": [[[19, 8192, [], [[[63, "W"], [62, "N"], [54, "N"], [46, "N"], [38, "N"], [30, "N"], [22, "N"]]], 0, 63, 14]], [[37, 8192, [], [[[63, "W"], [62, "W"], [61, "W"], [60, "W"], [59, "W"], [58, "W"]]], 0, 63, 57]]], "input_links": [], "start_time": 0, "visited": 0, "total_needSend": 16384, "end_time": 0, "total_needReceive": 8192, "mapto": 63, "exe_time": 3939}, "9": {"out_links": [[[20, 8192, [], [[[35, "N"], [27, "W"], [26, "W"]]], 0, 35, 25]], [[37, 8192, [], [[[35, "S"], [43, "S"], [51, "S"], [59, "W"], [58, "W"]]], 0, 35, 57]]], "input_links": [], "start_time": 0, "visited": 0, "total_needSend": 16384, "end_time": 0, "total_needReceive": 8192, "mapto": 35, "exe_time": 1863}, "10": {"out_links": [[[21, 8192, [], [[[7, "W"], [6, "W"], [5, "S"], [13, "W"], [12, "W"], [11, "S"], [19, "S"]]], 0, 7, 27]], [[37, 8192, [], [[[7, "S"], [15, "W"], [14, "W"], [13, "S"], [21, "W"], [20, "W"], [19, "W"], [18, "W"], [17, "S"], [25, "S"], [33, "S"], [41, "S"], [49, "S"]]], 0, 7, 57]]], "input_links": [], "start_time": 0, "visited": 0, "total_needSend": 16384, "end_time": 0, "total_needReceive": 8192, "mapto": 7, "exe_time": 5465}, "11": {"out_links": [[[22, 8192, [], [[[4, "W"], [3, "S"], [11, "S"], [19, "S"], [27, "S"]]], 0, 4, 35]], [[37, 8192, [], [[[4, "S"], [12, "W"], [11, "W"], [10, "W"], [9, "S"], [17, "S"], [25, "S"], [33, "S"], [41, "S"], [49, "S"]]], 0, 4, 57]]], "input_links": [], "start_time": 0, "visited": 0, "total_needSend": 16384, "end_time": 0, "total_needReceive": 8192, "mapto": 4, "exe_time": 4630}, "12": {"out_links": [[[23, 8192, [], [[[30, "E"], [31, "S"], [39, "S"]]], 0, 30, 47]], [[37, 8192, [], [[[30, "W"], [29, "W"], [28, "W"], [27, "W"], [26, "W"], [25, "S"], [33, "S"], [41, "S"], [49, "S"]]], 0, 30, 57]]], "input_links": [], "start_time": 0, "visited": 0, "total_needSend": 16384, "end_time": 0, "total_needReceive": 8192, "mapto": 30, "exe_time": 5932}, "13": {"out_links": [[[24, 8192, [], [[[38, "S"], [46, "E"]]], 0, 38, 47]], [[37, 8192, [], [[[38, "W"], [37, "S"], [45, "S"], [53, "W"], [52, "S"], [60, "W"], [59, "W"], [58, "W"]]], 0, 38, 57]]], "input_links": [], "start_time": 0, "visited": 0, "total_needSend": 16384, "end_time": 0, "total_needReceive": 8192, "mapto": 38, "exe_time": 5696}, "14": {"out_links": [[[25, 8192, [], [[[46, "W"], [45, "W"], [44, "W"], [43, "W"], [42, "S"], [50, "S"]]], 0, 46, 58]], [[37, 8192, [], [[[46, "S"], [54, "S"], [62, "W"], [61, "W"], [60, "W"], [59, "W"], [58, "W"]]], 0, 46, 57]]], "input_links": [], "start_time": 0, "visited": 0, "total_needSend": 16384, "end_time": 0, "total_needReceive": 8192, "mapto": 46, "exe_time": 6860}, "16": {"out_links": [[[27, 8192, [], [[[55, "W"], [54, "W"], [53, "W"], [52, "N"], [44, "W"], [43, "W"], [42, "W"], [41, "W"]]], 0, 55, 40]]], "input_links": [], "start_time": 0, "visited": 0, "total_needSend": 8192, "end_time": 0, "total_needReceive": 8192, "mapto": 55, "exe_time": 1986}, "37": {"out_links": [[[38, 8192, [], [[[57, "N"], [49, "N"], [41, "E"], [42, "E"], [43, "E"], [44, "E"]]], 0, 57, 45]]], "input_links": [], "start_time": 0, "visited": 0, "total_needSend": 8192, "end_time": 0, "total_needReceive": 90112, "mapto": 57, "exe_time": 1957}, "15": {"out_links": [[[26, 8192, [], [[[50, "N"]]], 0, 50, 42]]], "input_links": [], "start_time": 0, "visited": 0, "total_needSend": 8192, "end_time": 0, "total_needReceive": 8192, "mapto": 50, "exe_time": 1140}, "18": {"out_links": [[[29, 8192, [], [[[52, "N"], [44, "N"], [36, "N"], [28, "N"]]], 0, 52, 20]]], "input_links": [], "start_time": 0, "visited": 0, "total_needSend": 8192, "end_time": 0, "total_needReceive": 8192, "mapto": 52, "exe_time": 4913}, "17": {"out_links": [[[28, 8192, [], [[[61, "N"], [53, "E"], [54, "E"], [55, "N"]]], 0, 61, 47]]], "input_links": [], "start_time": 0, "visited": 0, "total_needSend": 8192, "end_time": 0, "total_needReceive": 8192, "mapto": 61, "exe_time": 8056}, "20": {"out_links": [[[31, 8192, [], [[[25, "E"], [26, "S"], [34, "E"]]], 0, 25, 35]]], "input_links": [], "start_time": 0, "visited": 0, "total_needSend": 8192, "end_time": 0, "total_needReceive": 8192, "mapto": 25, "exe_time": 6297}, "27": {"out_links": [], "input_links": [], "start_time": 0, "visited": 0, "total_needSend": 0, "end_time": 0, "total_needReceive": 16384, "mapto": 40, "exe_time": 4365}, "19": {"out_links": [[[30, 8192, [], [[[14, "S"], [22, "W"], [21, "S"], [29, "S"], [37, "S"]]], 0, 14, 45]]], "input_links": [], "start_time": 0, "visited": 0, "total_needSend": 8192, "end_time": 0, "total_needReceive": 8192, "mapto": 14, "exe_time": 5049}, "26": {"out_links": [], "input_links": [], "start_time": 0, "visited": 0, "total_needSend": 0, "end_time": 0, "total_needReceive": 16384, "mapto": 42, "exe_time": 1557}, "21": {"out_links": [[[32, 8192, [], [[[27, "W"], [26, "N"], [18, "N"], [10, "N"], [2, "W"]]], 0, 27, 1]]], "input_links": [], "start_time": 0, "visited": 0, "total_needSend": 8192, "end_time": 0, "total_needReceive": 8192, "mapto": 27, "exe_time": 3434}, "25": {"out_links": [[[36, 8192, [], [[[58, "N"], [50, "N"], [42, "N"], [34, "E"], [35, "N"], [27, "N"], [19, "N"], [11, "N"], [3, "E"]]], 0, 58, 4]]], "input_links": [], "start_time": 0, "visited": 0, "total_needSend": 8192, "end_time": 0, "total_needReceive": 8192, "mapto": 58, "exe_time": 4957}, "29": {"out_links": [], "input_links": [], "start_time": 0, "visited": 0, "total_needSend": 0, "end_time": 0, "total_needReceive": 16384, "mapto": 20, "exe_time": 1397}, "22": {"out_links": [[[33, 8192, [], [[[35, "E"], [36, "S"], [44, "S"], [52, "E"], [53, "E"]]], 0, 35, 54]]], "input_links": [], "start_time": 0, "visited": 0, "total_needSend": 8192, "end_time": 0, "total_needReceive": 8192, "mapto": 35, "exe_time": 4196}, "23": {"out_links": [[[34, 8192, [], [[[47, "N"], [39, "N"], [31, "N"], [23, "N"], [15, "W"], [14, "N"], [6, "W"]]], 0, 47, 5]]], "input_links": [], "start_time": 0, "visited": 0, "total_needSend": 8192, "end_time": 0, "total_needReceive": 8192, "mapto": 47, "exe_time": 2273}, "31": {"out_links": [], "input_links": [], "start_time": 0, "visited": 0, "total_needSend": 0, "end_time": 0, "total_needReceive": 16384, "mapto": 35, "exe_time": 5791}, "28": {"out_links": [], "input_links": [], "start_time": 0, "visited": 0, "total_needSend": 0, "end_time": 0, "total_needReceive": 16384, "mapto": 47, "exe_time": 2090}, "32": {"out_links": [], "input_links": [], "start_time": 0, "visited": 0, "total_needSend": 0, "end_time": 0, "total_needReceive": 16384, "mapto": 1, "exe_time": 2489}, "24": {"out_links": [[[35, 8192, [], [[[47, "S"], [55, "W"], [54, "W"]]], 0, 47, 53]]], "input_links": [], "start_time": 0, "visited": 0, "total_needSend": 8192, "end_time": 0, "total_needReceive": 8192, "mapto": 47, "exe_time": 9430}, "30": {"out_links": [], "input_links": [], "start_time": 0, "visited": 0, "total_needSend": 0, "end_time": 0, "total_needReceive": 16384, "mapto": 45, "exe_time": 3082}, "34": {"out_links": [], "input_links": [], "start_time": 0, "visited": 0, "total_needSend": 0, "end_time": 0, "total_needReceive": 16384, "mapto": 5, "exe_time": 900}, "33": {"out_links": [], "input_links": [], "start_time": 0, "visited": 0, "total_needSend": 0, "end_time": 0, "total_needReceive": 16384, "mapto": 54, "exe_time": 3033}, "36": {"out_links": [], "input_links": [], "start_time": 0, "visited": 0, "total_needSend": 0, "end_time": 0, "total_needReceive": 16384, "mapto": 4, "exe_time": 1132}, "35": {"out_links": [], "input_links": [], "start_time": 0, "visited": 0, "total_needSend": 0, "end_time": 0, "total_needReceive": 16384, "mapto": 53, "exe_time": 8560}, "38": {"out_links": [[[39, 8192, [], [[[45, "W"], [44, "N"], [36, "W"], [35, "W"]]], 0, 45, 34]], [[40, 8192, [], [[[45, "N"], [37, "N"], [29, "W"], [28, "W"]]], 0, 45, 27]], [[41, 8192, [], [[[45, "N"], [37, "W"], [36, "W"], [35, "W"], [34, "W"]]], 0, 45, 33]], [[42, 8192, [], [[[45, "E"], [46, "N"], [38, "N"], [30, "N"], [22, "N"]]], 0, 45, 14]], [[43, 8192, [], [[[45, "W"], [44, "W"], [43, "N"], [35, "N"], [27, "N"], [19, "N"]]], 0, 45, 11]], [[44, 8192, [], [[[45, "S"], [53, "W"], [52, "W"]]], 0, 45, 51]], [[45, 8192, [], [[[45, "E"], [46, "N"], [38, "N"]]], 0, 45, 30]], [[46, 8192, [], [[[45, "E"]]], 0, 45, 46]], [[47, 8192, [], [[]], 0, 45, 45]], [[48, 8192, [], [[[45, "S"], [53, "W"], [52, "W"], [51, "W"], [50, "W"]]], 0, 45, 49]], [[49, 8192, [], [[[45, "S"], [53, "S"], [61, "W"], [60, "W"], [59, "W"], [58, "W"]]], 0, 45, 57]], [[50, 8192, [], [[]], 0, 45, 45]]], "input_links": [], "start_time": 0, "visited": 0, "total_needSend": 98304, "end_time": 0, "total_needReceive": 8192, "mapto": 45, "exe_time": 2296}, "39": {"out_links": [[[26, 8192, [], [[[34, "S"]]], 0, 34, 42]]], "input_links": [], "start_time": 0, "visited": 0, "total_needSend": 8192, "end_time": 0, "total_needReceive": 8192, "mapto": 34, "exe_time": 3907}, "40": {"out_links": [[[27, 8192, [], [[[27, "W"], [26, "W"], [25, "W"], [24, "S"], [32, "S"]]], 0, 27, 40]]], "input_links": [], "start_time": 0, "visited": 0, "total_needSend": 8192, "end_time": 0, "total_needReceive": 8192, "mapto": 27, "exe_time": 6661}, "41": {"out_links": [[[28, 8192, [], [[[33, "E"], [34, "E"], [35, "E"], [36, "E"], [37, "E"], [38, "S"], [46, "E"]]], 0, 33, 47]]], "input_links": [], "start_time": 0, "visited": 0, "total_needSend": 8192, "end_time": 0, "total_needReceive": 8192, "mapto": 33, "exe_time": 396}, "42": {"out_links": [[[29, 8192, [], [[[14, "W"], [13, "W"], [12, "S"]]], 0, 14, 20]]], "input_links": [], "start_time": 0, "visited": 0, "total_needSend": 8192, "end_time": 0, "total_needReceive": 8192, "mapto": 14, "exe_time": 4014}, "43": {"out_links": [[[30, 8192, [], [[[11, "S"], [19, "E"], [20, "S"], [28, "S"], [36, "S"], [44, "E"]]], 0, 11, 45]]], "input_links": [], "start_time": 0, "visited": 0, "total_needSend": 8192, "end_time": 0, "total_needReceive": 8192, "mapto": 11, "exe_time": 3099}, "44": {"out_links": [[[31, 8192, [], [[[51, "N"], [43, "N"]]], 0, 51, 35]]], "input_links": [], "start_time": 0, "visited": 0, "total_needSend": 8192, "end_time": 0, "total_needReceive": 8192, "mapto": 51, "exe_time": 3082}, "45": {"out_links": [[[32, 8192, [], [[[30, "N"], [22, "N"], [14, "N"], [6, "W"], [5, "W"], [4, "W"], [3, "W"], [2, "W"]]], 0, 30, 1]]], "input_links": [], "start_time": 0, "visited": 0, "total_needSend": 8192, "end_time": 0, "total_needReceive": 8192, "mapto": 30, "exe_time": 2613}, "46": {"out_links": [[[33, 8192, [], [[[46, "S"]]], 0, 46, 54]]], "input_links": [], "start_time": 0, "visited": 0, "total_needSend": 8192, "end_time": 0, "total_needReceive": 8192, "mapto": 46, "exe_time": 4125}, "47": {"out_links": [[[34, 8192, [], [[[45, "N"], [37, "N"], [29, "N"], [21, "N"], [13, "N"]]], 0, 45, 5]]], "input_links": [], "start_time": 0, "visited": 0, "total_needSend": 8192, "end_time": 0, "total_needReceive": 8192, "mapto": 45, "exe_time": 4230}, "48": {"out_links": [[[35, 8192, [], [[[49, "E"], [50, "E"], [51, "E"], [52, "E"]]], 0, 49, 53]]], "input_links": [], "start_time": 0, "visited": 0, "total_needSend": 8192, "end_time": 0, "total_needReceive": 8192, "mapto": 49, "exe_time": 3908}, "49": {"out_links": [[[36, 8192, [], [[[57, "N"], [49, "N"], [41, "E"], [42, "N"], [34, "N"], [26, "N"], [18, "N"], [10, "E"], [11, "E"], [12, "N"]]], 0, 57, 4]]], "input_links": [], "start_time": 0, "visited": 0, "total_needSend": 8192, "end_time": 0, "total_needReceive": 8192, "mapto": 57, "exe_time": 370}, "50": {"out_links": [], "input_links": [], "start_time": 0, "visited": 0, "total_needSend": 0, "end_time": 0, "total_needReceive": 8192, "mapto": 45, "exe_time": 2806}}