{"0": {"total_needReceive": 0, "input_links": [], "start_time": 0, "out_links": [[[1, 1, [], [[[42, "E"], [43, "S"], [51, "S"], [59, "E"]]], 0, 42, 60]], [[13, 1, [], [[[42, "N"], [34, "N"], [26, "E"], [27, "E"]]], 0, 42, 28]], [[25, 1, [], [[[42, "W"], [41, "N"], [33, "N"], [25, "W"]]], 0, 42, 24]], [[37, 1, [], [[[42, "S"], [50, "S"], [58, "W"], [57, "W"]]], 0, 42, 56]], [[49, 1, [], [[[42, "S"], [50, "S"], [58, "E"], [59, "E"]]], 0, 42, 60]], [[61, 1, [], [[[42, "E"], [43, "E"], [44, "N"], [36, "N"]]], 0, 42, 28]], [[73, 1, [], [[[42, "W"], [41, "W"], [40, "N"], [32, "N"]]], 0, 42, 24]], [[85, 1, [], [[[42, "W"], [41, "W"], [40, "S"], [48, "S"]]], 0, 42, 56]], [[97, 1, [], [[[42, "E"], [43, "E"], [44, "S"], [52, "S"]]], 0, 42, 60]], [[109, 1, [], [[[42, "N"], [34, "N"], [26, "E"], [27, "E"]]], 0, 42, 28]], [[121, 1, [], [[[42, "N"], [34, "N"], [26, "W"], [25, "W"]]], 0, 42, 24]], [[133, 1, [], [[[42, "S"], [50, "S"], [58, "W"], [57, "W"]]], 0, 42, 56]], [[145, 1, [], [[[42, "S"], [50, "S"], [58, "E"], [59, "E"]]], 0, 42, 60]], [[157, 1, [], [[[42, "E"], [43, "E"], [44, "N"], [36, "N"]]], 0, 42, 28]], [[169, 1, [], [[[42, "N"], [34, "N"], [26, "W"], [25, "W"]]], 0, 42, 24]], [[181, 1, [], [[[42, "W"], [41, "W"], [40, "S"], [48, "S"]]], 0, 42, 56]], [[193, 1, [], [[[42, "S"], [50, "S"], [58, "E"], [59, "E"]]], 0, 42, 60]], [[205, 1, [], [[[42, "N"], [34, "N"], [26, "E"], [27, "E"]]], 0, 42, 28]], [[217, 1, [], [[[42, "W"], [41, "W"], [40, "N"], [32, "N"]]], 0, 42, 24]], [[229, 1, [], [[[42, "W"], [41, "W"], [40, "S"], [48, "S"]]], 0, 42, 56]], [[241, 1, [], [[[42, "E"], [43, "E"], [44, "S"], [52, "S"]]], 0, 42, 60]], [[253, 1, [], [[[42, "N"], [34, "N"], [26, "E"], [27, "E"]]], 0, 42, 28]], [[265, 1, [], [[[42, "W"], [41, "W"], [40, "N"], [32, "N"]]], 0, 42, 24]], [[277, 1, [], [[[42, "S"], [50, "S"], [58, "W"], [57, "W"]]], 0, 42, 56]]], "end_time": 0, "visited": 0, "total_needSend": 24, "exe_time": 0, "mapto": 42}, "1": {"total_needReceive": 1, "input_links": [], "start_time": 0, "out_links": [[[2, 93, [], [[[60, "E"], [61, "N"], [53, "N"], [45, "N"], [37, "N"]]], 0, 60, 29]]], "end_time": 0, "visited": 0, "total_needSend": 93, "exe_time": 0, "mapto": 60}, "2": {"total_needReceive": 93, "input_links": [], "start_time": 0, "out_links": [[[4, 93, [], [[[29, "S"], [37, "S"], [45, "E"], [46, "E"]]], 0, 29, 47]], [[5, 93, [], [[[29, "N"], [21, "N"], [13, "E"], [14, "E"]]], 0, 29, 15]], [[6, 93, [], [[[29, "W"], [28, "W"], [27, "N"], [19, "N"]]], 0, 29, 11]], [[7, 93, [], [[[29, "S"], [37, "S"], [45, "W"], [44, "W"]]], 0, 29, 43]], [[8, 93, [], [[[29, "E"], [30, "E"], [31, "S"], [39, "S"]]], 0, 29, 47]], [[9, 93, [], [[[29, "E"], [30, "E"], [31, "N"], [23, "N"]]], 0, 29, 15]], [[10, 93, [], [[[29, "N"], [21, "N"], [13, "W"], [12, "W"]]], 0, 29, 11]], [[11, 93, [], [[[29, "W"], [28, "W"], [27, "S"], [35, "S"]]], 0, 29, 43]]], "end_time": 0, "visited": 0, "total_needSend": 744, "exe_time": 29, "mapto": 29}, "3": {"total_needReceive": 744, "input_links": [], "start_time": 0, "out_links": [[[12, 93, [], [[[19, "E"], [20, "E"], [21, "S"], [29, "S"]]], 0, 19, 37]]], "end_time": 0, "visited": 0, "total_needSend": 93, "exe_time": 779, "mapto": 19}, "4": {"total_needReceive": 93, "input_links": [], "start_time": 0, "out_links": [[[3, 93, [], [[[47, "N"], [39, "N"], [31, "N"], [23, "W"], [22, "W"], [21, "W"], [20, "W"]]], 0, 47, 19]]], "end_time": 0, "visited": 0, "total_needSend": 93, "exe_time": 193, "mapto": 47}, "5": {"total_needReceive": 93, "input_links": [], "start_time": 0, "out_links": [[[3, 93, [], [[[15, "S"], [23, "W"], [22, "W"], [21, "W"], [20, "W"]]], 0, 15, 19]]], "end_time": 0, "visited": 0, "total_needSend": 93, "exe_time": 9, "mapto": 15}, "6": {"total_needReceive": 93, "input_links": [], "start_time": 0, "out_links": [[[3, 93, [], [[[11, "S"]]], 0, 11, 19]]], "end_time": 0, "visited": 0, "total_needSend": 93, "exe_time": 27, "mapto": 11}, "7": {"total_needReceive": 93, "input_links": [], "start_time": 0, "out_links": [[[3, 93, [], [[[43, "N"], [35, "N"], [27, "N"]]], 0, 43, 19]]], "end_time": 0, "visited": 0, "total_needSend": 93, "exe_time": 172, "mapto": 43}, "8": {"total_needReceive": 93, "input_links": [], "start_time": 0, "out_links": [[[3, 93, [], [[[47, "N"], [39, "N"], [31, "N"], [23, "W"], [22, "W"], [21, "W"], [20, "W"]]], 0, 47, 19]]], "end_time": 0, "visited": 0, "total_needSend": 93, "exe_time": 97, "mapto": 47}, "9": {"total_needReceive": 93, "input_links": [], "start_time": 0, "out_links": [[[3, 93, [], [[[15, "S"], [23, "W"], [22, "W"], [21, "W"], [20, "W"]]], 0, 15, 19]]], "end_time": 0, "visited": 0, "total_needSend": 93, "exe_time": 178, "mapto": 15}, "10": {"total_needReceive": 93, "input_links": [], "start_time": 0, "out_links": [[[3, 93, [], [[[11, "S"]]], 0, 11, 19]]], "end_time": 0, "visited": 0, "total_needSend": 93, "exe_time": 49, "mapto": 11}, "11": {"total_needReceive": 93, "input_links": [], "start_time": 0, "out_links": [[[3, 93, [], [[[43, "N"], [35, "N"], [27, "N"]]], 0, 43, 19]]], "end_time": 0, "visited": 0, "total_needSend": 93, "exe_time": 33, "mapto": 43}, "12": {"total_needReceive": 93, "input_links": [], "start_time": 0, "out_links": [[[289, 1, [], [[]], 0, 37, 37]]], "end_time": 0, "visited": 0, "total_needSend": 1, "exe_time": 123, "mapto": 37}, "13": {"total_needReceive": 1, "input_links": [], "start_time": 0, "out_links": [[[14, 93, [], [[[28, "W"], [27, "S"], [35, "S"]]], 0, 28, 43]]], "end_time": 0, "visited": 0, "total_needSend": 93, "exe_time": 29, "mapto": 28}, "14": {"total_needReceive": 93, "input_links": [], "start_time": 0, "out_links": [[[16, 93, [], [[[43, "S"], [51, "S"], [59, "E"], [60, "E"]]], 0, 43, 61]], [[17, 93, [], [[[43, "N"], [35, "N"], [27, "E"], [28, "E"]]], 0, 43, 29]], [[18, 93, [], [[[43, "W"], [42, "N"], [34, "W"], [33, "N"]]], 0, 43, 25]], [[19, 93, [], [[[43, "S"], [51, "S"], [59, "W"], [58, "W"]]], 0, 43, 57]], [[20, 93, [], [[[43, "E"], [44, "E"], [45, "S"], [53, "S"]]], 0, 43, 61]], [[21, 93, [], [[[43, "N"], [35, "N"], [27, "E"], [28, "E"]]], 0, 43, 29]], [[22, 93, [], [[[43, "N"], [35, "N"], [27, "W"], [26, "W"]]], 0, 43, 25]], [[23, 93, [], [[[43, "W"], [42, "W"], [41, "S"], [49, "S"]]], 0, 43, 57]]], "end_time": 0, "visited": 0, "total_needSend": 744, "exe_time": 28, "mapto": 43}, "15": {"total_needReceive": 744, "input_links": [], "start_time": 0, "out_links": [[[24, 93, [], [[[37, "E"], [38, "E"], [39, "S"], [47, "S"]]], 0, 37, 55]]], "end_time": 0, "visited": 0, "total_needSend": 93, "exe_time": 980, "mapto": 37}, "16": {"total_needReceive": 93, "input_links": [], "start_time": 0, "out_links": [[[15, 93, [], [[[61, "N"], [53, "N"], [45, "N"]]], 0, 61, 37]]], "end_time": 0, "visited": 0, "total_needSend": 93, "exe_time": 110, "mapto": 61}, "17": {"total_needReceive": 93, "input_links": [], "start_time": 0, "out_links": [[[15, 93, [], [[[29, "S"]]], 0, 29, 37]]], "end_time": 0, "visited": 0, "total_needSend": 93, "exe_time": 13, "mapto": 29}, "18": {"total_needReceive": 93, "input_links": [], "start_time": 0, "out_links": [[[15, 93, [], [[[25, "S"], [33, "E"], [34, "E"], [35, "E"], [36, "E"]]], 0, 25, 37]]], "end_time": 0, "visited": 0, "total_needSend": 93, "exe_time": 8, "mapto": 25}, "19": {"total_needReceive": 93, "input_links": [], "start_time": 0, "out_links": [[[15, 93, [], [[[57, "N"], [49, "E"], [50, "E"], [51, "E"], [52, "E"], [53, "N"], [45, "N"]]], 0, 57, 37]]], "end_time": 0, "visited": 0, "total_needSend": 93, "exe_time": 125, "mapto": 57}, "20": {"total_needReceive": 93, "input_links": [], "start_time": 0, "out_links": [[[15, 93, [], [[[61, "N"], [53, "N"], [45, "N"]]], 0, 61, 37]]], "end_time": 0, "visited": 0, "total_needSend": 93, "exe_time": 144, "mapto": 61}, "21": {"total_needReceive": 93, "input_links": [], "start_time": 0, "out_links": [[[15, 93, [], [[[29, "S"]]], 0, 29, 37]]], "end_time": 0, "visited": 0, "total_needSend": 93, "exe_time": 65, "mapto": 29}, "22": {"total_needReceive": 93, "input_links": [], "start_time": 0, "out_links": [[[15, 93, [], [[[25, "S"], [33, "E"], [34, "E"], [35, "E"], [36, "E"]]], 0, 25, 37]]], "end_time": 0, "visited": 0, "total_needSend": 93, "exe_time": 144, "mapto": 25}, "23": {"total_needReceive": 93, "input_links": [], "start_time": 0, "out_links": [[[15, 93, [], [[[57, "N"], [49, "E"], [50, "E"], [51, "E"], [52, "E"], [53, "N"], [45, "N"]]], 0, 57, 37]]], "end_time": 0, "visited": 0, "total_needSend": 93, "exe_time": 77, "mapto": 57}, "24": {"total_needReceive": 93, "input_links": [], "start_time": 0, "out_links": [[[289, 1, [], [[[55, "N"], [47, "W"], [46, "W"], [45, "N"]]], 0, 55, 37]]], "end_time": 0, "visited": 0, "total_needSend": 1, "exe_time": 32, "mapto": 55}, "25": {"total_needReceive": 1, "input_links": [], "start_time": 0, "out_links": [[[26, 93, [], [[[24, "E"], [25, "S"], [33, "S"], [41, "E"], [42, "E"]]], 0, 24, 43]]], "end_time": 0, "visited": 0, "total_needSend": 93, "exe_time": 137, "mapto": 24}, "26": {"total_needReceive": 93, "input_links": [], "start_time": 0, "out_links": [[[28, 93, [], [[[43, "S"], [51, "S"], [59, "E"], [60, "E"]]], 0, 43, 61]], [[29, 93, [], [[[43, "N"], [35, "N"], [27, "E"], [28, "E"]]], 0, 43, 29]], [[30, 93, [], [[[43, "W"], [42, "W"], [41, "N"], [33, "N"]]], 0, 43, 25]], [[31, 93, [], [[[43, "S"], [51, "S"], [59, "W"], [58, "W"]]], 0, 43, 57]], [[32, 93, [], [[[43, "S"], [51, "S"], [59, "E"], [60, "E"]]], 0, 43, 61]], [[33, 93, [], [[[43, "E"], [44, "E"], [45, "N"], [37, "N"]]], 0, 43, 29]], [[34, 93, [], [[[43, "W"], [42, "W"], [41, "N"], [33, "N"]]], 0, 43, 25]], [[35, 93, [], [[[43, "S"], [51, "S"], [59, "W"], [58, "W"]]], 0, 43, 57]]], "end_time": 0, "visited": 0, "total_needSend": 744, "exe_time": 55, "mapto": 43}, "27": {"total_needReceive": 744, "input_links": [], "start_time": 0, "out_links": [[[36, 93, [], [[[44, "E"], [45, "S"], [53, "S"], [61, "E"]]], 0, 44, 62]]], "end_time": 0, "visited": 0, "total_needSend": 93, "exe_time": 233, "mapto": 44}, "28": {"total_needReceive": 93, "input_links": [], "start_time": 0, "out_links": [[[27, 93, [], [[[61, "N"], [53, "W"], [52, "N"]]], 0, 61, 44]]], "end_time": 0, "visited": 0, "total_needSend": 93, "exe_time": 206, "mapto": 61}, "29": {"total_needReceive": 93, "input_links": [], "start_time": 0, "out_links": [[[27, 93, [], [[[29, "S"], [37, "S"], [45, "W"]]], 0, 29, 44]]], "end_time": 0, "visited": 0, "total_needSend": 93, "exe_time": 34, "mapto": 29}, "30": {"total_needReceive": 93, "input_links": [], "start_time": 0, "out_links": [[[27, 93, [], [[[25, "S"], [33, "S"], [41, "E"], [42, "E"], [43, "E"]]], 0, 25, 44]]], "end_time": 0, "visited": 0, "total_needSend": 93, "exe_time": 3, "mapto": 25}, "31": {"total_needReceive": 93, "input_links": [], "start_time": 0, "out_links": [[[27, 93, [], [[[57, "E"], [58, "E"], [59, "E"], [60, "N"], [52, "N"]]], 0, 57, 44]]], "end_time": 0, "visited": 0, "total_needSend": 93, "exe_time": 106, "mapto": 57}, "32": {"total_needReceive": 93, "input_links": [], "start_time": 0, "out_links": [[[27, 93, [], [[[61, "W"], [60, "N"], [52, "N"]]], 0, 61, 44]]], "end_time": 0, "visited": 0, "total_needSend": 93, "exe_time": 238, "mapto": 61}, "33": {"total_needReceive": 93, "input_links": [], "start_time": 0, "out_links": [[[27, 93, [], [[[29, "S"], [37, "S"], [45, "W"]]], 0, 29, 44]]], "end_time": 0, "visited": 0, "total_needSend": 93, "exe_time": 78, "mapto": 29}, "34": {"total_needReceive": 93, "input_links": [], "start_time": 0, "out_links": [[[27, 93, [], [[[25, "S"], [33, "S"], [41, "E"], [42, "E"], [43, "E"]]], 0, 25, 44]]], "end_time": 0, "visited": 0, "total_needSend": 93, "exe_time": 116, "mapto": 25}, "35": {"total_needReceive": 93, "input_links": [], "start_time": 0, "out_links": [[[27, 93, [], [[[57, "N"], [49, "E"], [50, "E"], [51, "E"], [52, "N"]]], 0, 57, 44]]], "end_time": 0, "visited": 0, "total_needSend": 93, "exe_time": 88, "mapto": 57}, "36": {"total_needReceive": 93, "input_links": [], "start_time": 0, "out_links": [[[289, 1, [], [[[62, "N"], [54, "N"], [46, "N"], [38, "W"]]], 0, 62, 37]]], "end_time": 0, "visited": 0, "total_needSend": 1, "exe_time": 113, "mapto": 62}, "37": {"total_needReceive": 1, "input_links": [], "start_time": 0, "out_links": [[[38, 93, [], [[[56, "E"], [57, "N"], [49, "E"], [50, "E"], [51, "N"], [43, "E"], [44, "N"]]], 0, 56, 36]]], "end_time": 0, "visited": 0, "total_needSend": 93, "exe_time": 52, "mapto": 56}, "38": {"total_needReceive": 93, "input_links": [], "start_time": 0, "out_links": [[[40, 93, [], [[[36, "S"], [44, "S"], [52, "E"], [53, "E"]]], 0, 36, 54]], [[41, 93, [], [[[36, "E"], [37, "E"], [38, "N"], [30, "N"]]], 0, 36, 22]], [[42, 93, [], [[[36, "N"], [28, "N"], [20, "W"], [19, "W"]]], 0, 36, 18]], [[43, 93, [], [[[36, "S"], [44, "S"], [52, "W"], [51, "W"]]], 0, 36, 50]], [[44, 93, [], [[[36, "E"], [37, "E"], [38, "S"], [46, "S"]]], 0, 36, 54]], [[45, 93, [], [[[36, "E"], [37, "E"], [38, "N"], [30, "N"]]], 0, 36, 22]], [[46, 93, [], [[[36, "N"], [28, "N"], [20, "W"], [19, "W"]]], 0, 36, 18]], [[47, 93, [], [[[36, "S"], [44, "S"], [52, "W"], [51, "W"]]], 0, 36, 50]]], "end_time": 0, "visited": 0, "total_needSend": 744, "exe_time": 1, "mapto": 36}, "39": {"total_needReceive": 744, "input_links": [], "start_time": 0, "out_links": [[[48, 93, [], [[[19, "E"], [20, "E"], [21, "S"], [29, "S"]]], 0, 19, 37]]], "end_time": 0, "visited": 0, "total_needSend": 93, "exe_time": 1023, "mapto": 19}, "40": {"total_needReceive": 93, "input_links": [], "start_time": 0, "out_links": [[[39, 93, [], [[[54, "W"], [53, "W"], [52, "W"], [51, "N"], [43, "N"], [35, "N"], [27, "N"]]], 0, 54, 19]]], "end_time": 0, "visited": 0, "total_needSend": 93, "exe_time": 43, "mapto": 54}, "41": {"total_needReceive": 93, "input_links": [], "start_time": 0, "out_links": [[[39, 93, [], [[[22, "W"], [21, "W"], [20, "W"]]], 0, 22, 19]]], "end_time": 0, "visited": 0, "total_needSend": 93, "exe_time": 3, "mapto": 22}, "42": {"total_needReceive": 93, "input_links": [], "start_time": 0, "out_links": [[[39, 93, [], [[[18, "E"]]], 0, 18, 19]]], "end_time": 0, "visited": 0, "total_needSend": 93, "exe_time": 4, "mapto": 18}, "43": {"total_needReceive": 93, "input_links": [], "start_time": 0, "out_links": [[[39, 93, [], [[[50, "E"], [51, "N"], [43, "N"], [35, "N"], [27, "N"]]], 0, 50, 19]]], "end_time": 0, "visited": 0, "total_needSend": 93, "exe_time": 12, "mapto": 50}, "44": {"total_needReceive": 93, "input_links": [], "start_time": 0, "out_links": [[[39, 93, [], [[[54, "W"], [53, "W"], [52, "W"], [51, "N"], [43, "N"], [35, "N"], [27, "N"]]], 0, 54, 19]]], "end_time": 0, "visited": 0, "total_needSend": 93, "exe_time": 78, "mapto": 54}, "45": {"total_needReceive": 93, "input_links": [], "start_time": 0, "out_links": [[[39, 93, [], [[[22, "W"], [21, "W"], [20, "W"]]], 0, 22, 19]]], "end_time": 0, "visited": 0, "total_needSend": 93, "exe_time": 129, "mapto": 22}, "46": {"total_needReceive": 93, "input_links": [], "start_time": 0, "out_links": [[[39, 93, [], [[[18, "E"]]], 0, 18, 19]]], "end_time": 0, "visited": 0, "total_needSend": 93, "exe_time": 1, "mapto": 18}, "47": {"total_needReceive": 93, "input_links": [], "start_time": 0, "out_links": [[[39, 93, [], [[[50, "E"], [51, "N"], [43, "N"], [35, "N"], [27, "N"]]], 0, 50, 19]]], "end_time": 0, "visited": 0, "total_needSend": 93, "exe_time": 34, "mapto": 50}, "48": {"total_needReceive": 93, "input_links": [], "start_time": 0, "out_links": [[[289, 1, [], [[]], 0, 37, 37]]], "end_time": 0, "visited": 0, "total_needSend": 1, "exe_time": 139, "mapto": 37}, "49": {"total_needReceive": 1, "input_links": [], "start_time": 0, "out_links": [[[50, 93, [], [[[60, "W"], [59, "W"], [58, "N"], [50, "N"], [42, "N"], [34, "N"], [26, "N"]]], 0, 60, 18]]], "end_time": 0, "visited": 0, "total_needSend": 93, "exe_time": 86, "mapto": 60}, "50": {"total_needReceive": 93, "input_links": [], "start_time": 0, "out_links": [[[52, 93, [], [[[18, "E"], [19, "E"], [20, "S"], [28, "S"]]], 0, 18, 36]], [[53, 93, [], [[[18, "E"], [19, "N"], [11, "N"], [3, "E"]]], 0, 18, 4]], [[54, 93, [], [[[18, "W"], [17, "W"], [16, "N"], [8, "N"]]], 0, 18, 0]], [[55, 93, [], [[[18, "W"], [17, "W"], [16, "S"], [24, "S"]]], 0, 18, 32]], [[56, 93, [], [[[18, "E"], [19, "E"], [20, "S"], [28, "S"]]], 0, 18, 36]], [[57, 93, [], [[[18, "N"], [10, "N"], [2, "E"], [3, "E"]]], 0, 18, 4]], [[58, 93, [], [[[18, "W"], [17, "W"], [16, "N"], [8, "N"]]], 0, 18, 0]], [[59, 93, [], [[[18, "W"], [17, "W"], [16, "S"], [24, "S"]]], 0, 18, 32]]], "end_time": 0, "visited": 0, "total_needSend": 744, "exe_time": 224, "mapto": 18}, "51": {"total_needReceive": 744, "input_links": [], "start_time": 0, "out_links": [[[60, 93, [], [[[26, "E"], [27, "E"], [28, "S"], [36, "S"]]], 0, 26, 44]]], "end_time": 0, "visited": 0, "total_needSend": 93, "exe_time": 751, "mapto": 26}, "52": {"total_needReceive": 93, "input_links": [], "start_time": 0, "out_links": [[[51, 93, [], [[[36, "N"], [28, "W"], [27, "W"]]], 0, 36, 26]]], "end_time": 0, "visited": 0, "total_needSend": 93, "exe_time": 274, "mapto": 36}, "53": {"total_needReceive": 93, "input_links": [], "start_time": 0, "out_links": [[[51, 93, [], [[[4, "W"], [3, "W"], [2, "S"], [10, "S"], [18, "S"]]], 0, 4, 26]]], "end_time": 0, "visited": 0, "total_needSend": 93, "exe_time": 22, "mapto": 4}, "54": {"total_needReceive": 93, "input_links": [], "start_time": 0, "out_links": [[[51, 93, [], [[[0, "E"], [1, "S"], [9, "S"], [17, "S"], [25, "E"]]], 0, 0, 26]]], "end_time": 0, "visited": 0, "total_needSend": 93, "exe_time": 10, "mapto": 0}, "55": {"total_needReceive": 93, "input_links": [], "start_time": 0, "out_links": [[[51, 93, [], [[[32, "N"], [24, "E"], [25, "E"]]], 0, 32, 26]]], "end_time": 0, "visited": 0, "total_needSend": 93, "exe_time": 125, "mapto": 32}, "56": {"total_needReceive": 93, "input_links": [], "start_time": 0, "out_links": [[[51, 93, [], [[[36, "N"], [28, "W"], [27, "W"]]], 0, 36, 26]]], "end_time": 0, "visited": 0, "total_needSend": 93, "exe_time": 22, "mapto": 36}, "57": {"total_needReceive": 93, "input_links": [], "start_time": 0, "out_links": [[[51, 93, [], [[[4, "S"], [12, "W"], [11, "W"], [10, "S"], [18, "S"]]], 0, 4, 26]]], "end_time": 0, "visited": 0, "total_needSend": 93, "exe_time": 9, "mapto": 4}, "58": {"total_needReceive": 93, "input_links": [], "start_time": 0, "out_links": [[[51, 93, [], [[[0, "S"], [8, "E"], [9, "S"], [17, "S"], [25, "E"]]], 0, 0, 26]]], "end_time": 0, "visited": 0, "total_needSend": 93, "exe_time": 32, "mapto": 0}, "59": {"total_needReceive": 93, "input_links": [], "start_time": 0, "out_links": [[[51, 93, [], [[[32, "N"], [24, "E"], [25, "E"]]], 0, 32, 26]]], "end_time": 0, "visited": 0, "total_needSend": 93, "exe_time": 5, "mapto": 32}, "60": {"total_needReceive": 93, "input_links": [], "start_time": 0, "out_links": [[[289, 1, [], [[[44, "E"], [45, "N"]]], 0, 44, 37]]], "end_time": 0, "visited": 0, "total_needSend": 1, "exe_time": 74, "mapto": 44}, "61": {"total_needReceive": 1, "input_links": [], "start_time": 0, "out_links": [[[62, 93, [], [[[28, "N"], [20, "W"], [19, "W"]]], 0, 28, 18]]], "end_time": 0, "visited": 0, "total_needSend": 93, "exe_time": 48, "mapto": 28}, "62": {"total_needReceive": 93, "input_links": [], "start_time": 0, "out_links": [[[64, 93, [], [[[18, "E"], [19, "E"], [20, "S"], [28, "S"]]], 0, 18, 36]], [[65, 93, [], [[[18, "N"], [10, "N"], [2, "E"], [3, "E"]]], 0, 18, 4]], [[66, 93, [], [[[18, "W"], [17, "N"], [9, "N"], [1, "W"]]], 0, 18, 0]], [[67, 93, [], [[[18, "W"], [17, "S"], [25, "S"], [33, "W"]]], 0, 18, 32]], [[68, 93, [], [[[18, "S"], [26, "S"], [34, "E"], [35, "E"]]], 0, 18, 36]], [[69, 93, [], [[[18, "E"], [19, "E"], [20, "N"], [12, "N"]]], 0, 18, 4]], [[70, 93, [], [[[18, "W"], [17, "W"], [16, "N"], [8, "N"]]], 0, 18, 0]], [[71, 93, [], [[[18, "W"], [17, "W"], [16, "S"], [24, "S"]]], 0, 18, 32]]], "end_time": 0, "visited": 0, "total_needSend": 744, "exe_time": 53, "mapto": 18}, "63": {"total_needReceive": 744, "input_links": [], "start_time": 0, "out_links": [[[72, 93, [], [[[43, "S"], [51, "E"], [52, "S"], [60, "E"]]], 0, 43, 61]]], "end_time": 0, "visited": 0, "total_needSend": 93, "exe_time": 912, "mapto": 43}, "64": {"total_needReceive": 93, "input_links": [], "start_time": 0, "out_links": [[[63, 93, [], [[[36, "S"], [44, "W"]]], 0, 36, 43]]], "end_time": 0, "visited": 0, "total_needSend": 93, "exe_time": 97, "mapto": 36}, "65": {"total_needReceive": 93, "input_links": [], "start_time": 0, "out_links": [[[63, 93, [], [[[4, "W"], [3, "S"], [11, "S"], [19, "S"], [27, "S"], [35, "S"]]], 0, 4, 43]]], "end_time": 0, "visited": 0, "total_needSend": 93, "exe_time": 18, "mapto": 4}, "66": {"total_needReceive": 93, "input_links": [], "start_time": 0, "out_links": [[[63, 93, [], [[[0, "E"], [1, "E"], [2, "E"], [3, "S"], [11, "S"], [19, "S"], [27, "S"], [35, "S"]]], 0, 0, 43]]], "end_time": 0, "visited": 0, "total_needSend": 93, "exe_time": 2, "mapto": 0}, "67": {"total_needReceive": 93, "input_links": [], "start_time": 0, "out_links": [[[63, 93, [], [[[32, "S"], [40, "E"], [41, "E"], [42, "E"]]], 0, 32, 43]]], "end_time": 0, "visited": 0, "total_needSend": 93, "exe_time": 53, "mapto": 32}, "68": {"total_needReceive": 93, "input_links": [], "start_time": 0, "out_links": [[[63, 93, [], [[[36, "S"], [44, "W"]]], 0, 36, 43]]], "end_time": 0, "visited": 0, "total_needSend": 93, "exe_time": 160, "mapto": 36}, "69": {"total_needReceive": 93, "input_links": [], "start_time": 0, "out_links": [[[63, 93, [], [[[4, "W"], [3, "S"], [11, "S"], [19, "S"], [27, "S"], [35, "S"]]], 0, 4, 43]]], "end_time": 0, "visited": 0, "total_needSend": 93, "exe_time": 330, "mapto": 4}, "70": {"total_needReceive": 93, "input_links": [], "start_time": 0, "out_links": [[[63, 93, [], [[[0, "E"], [1, "E"], [2, "E"], [3, "S"], [11, "S"], [19, "S"], [27, "S"], [35, "S"]]], 0, 0, 43]]], "end_time": 0, "visited": 0, "total_needSend": 93, "exe_time": 37, "mapto": 0}, "71": {"total_needReceive": 93, "input_links": [], "start_time": 0, "out_links": [[[63, 93, [], [[[32, "S"], [40, "E"], [41, "E"], [42, "E"]]], 0, 32, 43]]], "end_time": 0, "visited": 0, "total_needSend": 93, "exe_time": 50, "mapto": 32}, "72": {"total_needReceive": 93, "input_links": [], "start_time": 0, "out_links": [[[289, 1, [], [[[61, "N"], [53, "N"], [45, "N"]]], 0, 61, 37]]], "end_time": 0, "visited": 0, "total_needSend": 1, "exe_time": 123, "mapto": 61}, "73": {"total_needReceive": 1, "input_links": [], "start_time": 0, "out_links": [[[74, 93, [], [[[24, "S"], [32, "E"], [33, "E"], [34, "E"], [35, "E"]]], 0, 24, 36]]], "end_time": 0, "visited": 0, "total_needSend": 93, "exe_time": 57, "mapto": 24}, "74": {"total_needReceive": 93, "input_links": [], "start_time": 0, "out_links": [[[76, 93, [], [[[36, "E"], [37, "E"], [38, "S"], [46, "S"]]], 0, 36, 54]], [[77, 93, [], [[[36, "E"], [37, "E"], [38, "N"], [30, "N"]]], 0, 36, 22]], [[78, 93, [], [[[36, "W"], [35, "W"], [34, "N"], [26, "N"]]], 0, 36, 18]], [[79, 93, [], [[[36, "W"], [35, "W"], [34, "S"], [42, "S"]]], 0, 36, 50]], [[80, 93, [], [[[36, "E"], [37, "E"], [38, "S"], [46, "S"]]], 0, 36, 54]], [[81, 93, [], [[[36, "E"], [37, "E"], [38, "N"], [30, "N"]]], 0, 36, 22]], [[82, 93, [], [[[36, "N"], [28, "N"], [20, "W"], [19, "W"]]], 0, 36, 18]], [[83, 93, [], [[[36, "W"], [35, "W"], [34, "S"], [42, "S"]]], 0, 36, 50]]], "end_time": 0, "visited": 0, "total_needSend": 744, "exe_time": 25, "mapto": 36}, "75": {"total_needReceive": 744, "input_links": [], "start_time": 0, "out_links": [[[84, 93, [], [[[26, "S"], [34, "E"], [35, "E"], [36, "S"]]], 0, 26, 44]]], "end_time": 0, "visited": 0, "total_needSend": 93, "exe_time": 569, "mapto": 26}, "76": {"total_needReceive": 93, "input_links": [], "start_time": 0, "out_links": [[[75, 93, [], [[[54, "N"], [46, "N"], [38, "N"], [30, "W"], [29, "W"], [28, "W"], [27, "W"]]], 0, 54, 26]]], "end_time": 0, "visited": 0, "total_needSend": 93, "exe_time": 78, "mapto": 54}, "77": {"total_needReceive": 93, "input_links": [], "start_time": 0, "out_links": [[[75, 93, [], [[[22, "S"], [30, "W"], [29, "W"], [28, "W"], [27, "W"]]], 0, 22, 26]]], "end_time": 0, "visited": 0, "total_needSend": 93, "exe_time": 6, "mapto": 22}, "78": {"total_needReceive": 93, "input_links": [], "start_time": 0, "out_links": [[[75, 93, [], [[[18, "S"]]], 0, 18, 26]]], "end_time": 0, "visited": 0, "total_needSend": 93, "exe_time": 5, "mapto": 18}, "79": {"total_needReceive": 93, "input_links": [], "start_time": 0, "out_links": [[[75, 93, [], [[[50, "N"], [42, "N"], [34, "N"]]], 0, 50, 26]]], "end_time": 0, "visited": 0, "total_needSend": 93, "exe_time": 64, "mapto": 50}, "80": {"total_needReceive": 93, "input_links": [], "start_time": 0, "out_links": [[[75, 93, [], [[[54, "N"], [46, "N"], [38, "N"], [30, "W"], [29, "W"], [28, "W"], [27, "W"]]], 0, 54, 26]]], "end_time": 0, "visited": 0, "total_needSend": 93, "exe_time": 39, "mapto": 54}, "81": {"total_needReceive": 93, "input_links": [], "start_time": 0, "out_links": [[[75, 93, [], [[[22, "W"], [21, "S"], [29, "W"], [28, "W"], [27, "W"]]], 0, 22, 26]]], "end_time": 0, "visited": 0, "total_needSend": 93, "exe_time": 163, "mapto": 22}, "82": {"total_needReceive": 93, "input_links": [], "start_time": 0, "out_links": [[[75, 93, [], [[[18, "S"]]], 0, 18, 26]]], "end_time": 0, "visited": 0, "total_needSend": 93, "exe_time": 160, "mapto": 18}, "83": {"total_needReceive": 93, "input_links": [], "start_time": 0, "out_links": [[[75, 93, [], [[[50, "N"], [42, "N"], [34, "N"]]], 0, 50, 26]]], "end_time": 0, "visited": 0, "total_needSend": 93, "exe_time": 36, "mapto": 50}, "84": {"total_needReceive": 93, "input_links": [], "start_time": 0, "out_links": [[[289, 1, [], [[[44, "N"], [36, "E"]]], 0, 44, 37]]], "end_time": 0, "visited": 0, "total_needSend": 1, "exe_time": 81, "mapto": 44}, "85": {"total_needReceive": 1, "input_links": [], "start_time": 0, "out_links": [[[86, 93, [], [[[56, "N"], [48, "N"], [40, "E"], [41, "E"], [42, "E"], [43, "E"], [44, "E"]]], 0, 56, 45]]], "end_time": 0, "visited": 0, "total_needSend": 93, "exe_time": 124, "mapto": 56}, "86": {"total_needReceive": 93, "input_links": [], "start_time": 0, "out_links": [[[88, 93, [], [[[45, "S"], [53, "S"], [61, "E"], [62, "E"]]], 0, 45, 63]], [[89, 93, [], [[[45, "E"], [46, "E"], [47, "N"], [39, "N"]]], 0, 45, 31]], [[90, 93, [], [[[45, "N"], [37, "N"], [29, "W"], [28, "W"]]], 0, 45, 27]], [[91, 93, [], [[[45, "S"], [53, "S"], [61, "W"], [60, "W"]]], 0, 45, 59]], [[92, 93, [], [[[45, "E"], [46, "E"], [47, "S"], [55, "S"]]], 0, 45, 63]], [[93, 93, [], [[[45, "E"], [46, "E"], [47, "N"], [39, "N"]]], 0, 45, 31]], [[94, 93, [], [[[45, "N"], [37, "N"], [29, "W"], [28, "W"]]], 0, 45, 27]], [[95, 93, [], [[[45, "S"], [53, "S"], [61, "W"], [60, "W"]]], 0, 45, 59]]], "end_time": 0, "visited": 0, "total_needSend": 744, "exe_time": 314, "mapto": 45}, "87": {"total_needReceive": 744, "input_links": [], "start_time": 0, "out_links": [[[96, 93, [], [[[26, "S"], [34, "S"], [42, "E"], [43, "E"]]], 0, 26, 44]]], "end_time": 0, "visited": 0, "total_needSend": 93, "exe_time": 802, "mapto": 26}, "88": {"total_needReceive": 93, "input_links": [], "start_time": 0, "out_links": [[[87, 93, [], [[[63, "N"], [55, "W"], [54, "N"], [46, "N"], [38, "N"], [30, "W"], [29, "W"], [28, "W"], [27, "W"]]], 0, 63, 26]]], "end_time": 0, "visited": 0, "total_needSend": 93, "exe_time": 129, "mapto": 63}, "89": {"total_needReceive": 93, "input_links": [], "start_time": 0, "out_links": [[[87, 93, [], [[[31, "W"], [30, "W"], [29, "W"], [28, "W"], [27, "W"]]], 0, 31, 26]]], "end_time": 0, "visited": 0, "total_needSend": 93, "exe_time": 7, "mapto": 31}, "90": {"total_needReceive": 93, "input_links": [], "start_time": 0, "out_links": [[[87, 93, [], [[[27, "W"]]], 0, 27, 26]]], "end_time": 0, "visited": 0, "total_needSend": 93, "exe_time": 2, "mapto": 27}, "91": {"total_needReceive": 93, "input_links": [], "start_time": 0, "out_links": [[[87, 93, [], [[[59, "W"], [58, "N"], [50, "N"], [42, "N"], [34, "N"]]], 0, 59, 26]]], "end_time": 0, "visited": 0, "total_needSend": 93, "exe_time": 306, "mapto": 59}, "92": {"total_needReceive": 93, "input_links": [], "start_time": 0, "out_links": [[[87, 93, [], [[[63, "N"], [55, "W"], [54, "N"], [46, "N"], [38, "N"], [30, "W"], [29, "W"], [28, "W"], [27, "W"]]], 0, 63, 26]]], "end_time": 0, "visited": 0, "total_needSend": 93, "exe_time": 23, "mapto": 63}, "93": {"total_needReceive": 93, "input_links": [], "start_time": 0, "out_links": [[[87, 93, [], [[[31, "W"], [30, "W"], [29, "W"], [28, "W"], [27, "W"]]], 0, 31, 26]]], "end_time": 0, "visited": 0, "total_needSend": 93, "exe_time": 32, "mapto": 31}, "94": {"total_needReceive": 93, "input_links": [], "start_time": 0, "out_links": [[[87, 93, [], [[[27, "W"]]], 0, 27, 26]]], "end_time": 0, "visited": 0, "total_needSend": 93, "exe_time": 198, "mapto": 27}, "95": {"total_needReceive": 93, "input_links": [], "start_time": 0, "out_links": [[[87, 93, [], [[[59, "W"], [58, "N"], [50, "N"], [42, "N"], [34, "N"]]], 0, 59, 26]]], "end_time": 0, "visited": 0, "total_needSend": 93, "exe_time": 20, "mapto": 59}, "96": {"total_needReceive": 93, "input_links": [], "start_time": 0, "out_links": [[[289, 1, [], [[[44, "E"], [45, "N"]]], 0, 44, 37]]], "end_time": 0, "visited": 0, "total_needSend": 1, "exe_time": 3, "mapto": 44}, "97": {"total_needReceive": 1, "input_links": [], "start_time": 0, "out_links": [[[98, 93, [], [[[60, "N"], [52, "N"], [44, "N"], [36, "N"], [28, "N"]]], 0, 60, 20]]], "end_time": 0, "visited": 0, "total_needSend": 93, "exe_time": 128, "mapto": 60}, "98": {"total_needReceive": 93, "input_links": [], "start_time": 0, "out_links": [[[100, 93, [], [[[20, "E"], [21, "E"], [22, "S"], [30, "S"]]], 0, 20, 38]], [[101, 93, [], [[[20, "N"], [12, "E"], [13, "E"], [14, "N"]]], 0, 20, 6]], [[102, 93, [], [[[20, "N"], [12, "N"], [4, "W"], [3, "W"]]], 0, 20, 2]], [[103, 93, [], [[[20, "S"], [28, "S"], [36, "W"], [35, "W"]]], 0, 20, 34]], [[104, 93, [], [[[20, "S"], [28, "E"], [29, "E"], [30, "S"]]], 0, 20, 38]], [[105, 93, [], [[[20, "N"], [12, "N"], [4, "E"], [5, "E"]]], 0, 20, 6]], [[106, 93, [], [[[20, "N"], [12, "N"], [4, "W"], [3, "W"]]], 0, 20, 2]], [[107, 93, [], [[[20, "S"], [28, "S"], [36, "W"], [35, "W"]]], 0, 20, 34]]], "end_time": 0, "visited": 0, "total_needSend": 744, "exe_time": 116, "mapto": 20}, "99": {"total_needReceive": 744, "input_links": [], "start_time": 0, "out_links": [[[108, 93, [], [[[44, "S"], [52, "E"], [53, "E"], [54, "S"]]], 0, 44, 62]]], "end_time": 0, "visited": 0, "total_needSend": 93, "exe_time": 848, "mapto": 44}, "100": {"total_needReceive": 93, "input_links": [], "start_time": 0, "out_links": [[[99, 93, [], [[[38, "S"], [46, "W"], [45, "W"]]], 0, 38, 44]]], "end_time": 0, "visited": 0, "total_needSend": 93, "exe_time": 313, "mapto": 38}, "101": {"total_needReceive": 93, "input_links": [], "start_time": 0, "out_links": [[[99, 93, [], [[[6, "S"], [14, "S"], [22, "S"], [30, "S"], [38, "S"], [46, "W"], [45, "W"]]], 0, 6, 44]]], "end_time": 0, "visited": 0, "total_needSend": 93, "exe_time": 3, "mapto": 6}, "102": {"total_needReceive": 93, "input_links": [], "start_time": 0, "out_links": [[[99, 93, [], [[[2, "E"], [3, "E"], [4, "S"], [12, "S"], [20, "S"], [28, "S"], [36, "S"]]], 0, 2, 44]]], "end_time": 0, "visited": 0, "total_needSend": 93, "exe_time": 4, "mapto": 2}, "103": {"total_needReceive": 93, "input_links": [], "start_time": 0, "out_links": [[[99, 93, [], [[[34, "S"], [42, "E"], [43, "E"]]], 0, 34, 44]]], "end_time": 0, "visited": 0, "total_needSend": 93, "exe_time": 74, "mapto": 34}, "104": {"total_needReceive": 93, "input_links": [], "start_time": 0, "out_links": [[[99, 93, [], [[[38, "W"], [37, "W"], [36, "S"]]], 0, 38, 44]]], "end_time": 0, "visited": 0, "total_needSend": 93, "exe_time": 188, "mapto": 38}, "105": {"total_needReceive": 93, "input_links": [], "start_time": 0, "out_links": [[[99, 93, [], [[[6, "S"], [14, "S"], [22, "S"], [30, "S"], [38, "S"], [46, "W"], [45, "W"]]], 0, 6, 44]]], "end_time": 0, "visited": 0, "total_needSend": 93, "exe_time": 28, "mapto": 6}, "106": {"total_needReceive": 93, "input_links": [], "start_time": 0, "out_links": [[[99, 93, [], [[[2, "E"], [3, "E"], [4, "S"], [12, "S"], [20, "S"], [28, "S"], [36, "S"]]], 0, 2, 44]]], "end_time": 0, "visited": 0, "total_needSend": 93, "exe_time": 145, "mapto": 2}, "107": {"total_needReceive": 93, "input_links": [], "start_time": 0, "out_links": [[[99, 93, [], [[[34, "S"], [42, "E"], [43, "E"]]], 0, 34, 44]]], "end_time": 0, "visited": 0, "total_needSend": 93, "exe_time": 394, "mapto": 34}, "108": {"total_needReceive": 93, "input_links": [], "start_time": 0, "out_links": [[[289, 1, [], [[[62, "N"], [54, "W"], [53, "N"], [45, "N"]]], 0, 62, 37]]], "end_time": 0, "visited": 0, "total_needSend": 1, "exe_time": 77, "mapto": 62}, "109": {"total_needReceive": 1, "input_links": [], "start_time": 0, "out_links": [[[110, 93, [], [[[28, "E"]]], 0, 28, 29]]], "end_time": 0, "visited": 0, "total_needSend": 93, "exe_time": 27, "mapto": 28}, "110": {"total_needReceive": 93, "input_links": [], "start_time": 0, "out_links": [[[112, 93, [], [[[29, "E"], [30, "E"], [31, "S"], [39, "S"]]], 0, 29, 47]], [[113, 93, [], [[[29, "E"], [30, "E"], [31, "N"], [23, "N"]]], 0, 29, 15]], [[114, 93, [], [[[29, "N"], [21, "N"], [13, "W"], [12, "W"]]], 0, 29, 11]], [[115, 93, [], [[[29, "S"], [37, "S"], [45, "W"], [44, "W"]]], 0, 29, 43]], [[116, 93, [], [[[29, "S"], [37, "S"], [45, "E"], [46, "E"]]], 0, 29, 47]], [[117, 93, [], [[[29, "N"], [21, "N"], [13, "E"], [14, "E"]]], 0, 29, 15]], [[118, 93, [], [[[29, "N"], [21, "N"], [13, "W"], [12, "W"]]], 0, 29, 11]], [[119, 93, [], [[[29, "S"], [37, "S"], [45, "W"], [44, "W"]]], 0, 29, 43]]], "end_time": 0, "visited": 0, "total_needSend": 744, "exe_time": 97, "mapto": 29}, "111": {"total_needReceive": 744, "input_links": [], "start_time": 0, "out_links": [[[120, 93, [], [[[42, "E"], [43, "S"], [51, "S"], [59, "E"]]], 0, 42, 60]]], "end_time": 0, "visited": 0, "total_needSend": 93, "exe_time": 127, "mapto": 42}, "112": {"total_needReceive": 93, "input_links": [], "start_time": 0, "out_links": [[[111, 93, [], [[[47, "W"], [46, "W"], [45, "W"], [44, "W"], [43, "W"]]], 0, 47, 42]]], "end_time": 0, "visited": 0, "total_needSend": 93, "exe_time": 50, "mapto": 47}, "113": {"total_needReceive": 93, "input_links": [], "start_time": 0, "out_links": [[[111, 93, [], [[[15, "S"], [23, "S"], [31, "S"], [39, "S"], [47, "W"], [46, "W"], [45, "W"], [44, "W"], [43, "W"]]], 0, 15, 42]]], "end_time": 0, "visited": 0, "total_needSend": 93, "exe_time": 8, "mapto": 15}, "114": {"total_needReceive": 93, "input_links": [], "start_time": 0, "out_links": [[[111, 93, [], [[[11, "W"], [10, "S"], [18, "S"], [26, "S"], [34, "S"]]], 0, 11, 42]]], "end_time": 0, "visited": 0, "total_needSend": 93, "exe_time": 3, "mapto": 11}, "115": {"total_needReceive": 93, "input_links": [], "start_time": 0, "out_links": [[[111, 93, [], [[[43, "W"]]], 0, 43, 42]]], "end_time": 0, "visited": 0, "total_needSend": 93, "exe_time": 39, "mapto": 43}, "116": {"total_needReceive": 93, "input_links": [], "start_time": 0, "out_links": [[[111, 93, [], [[[47, "W"], [46, "W"], [45, "W"], [44, "W"], [43, "W"]]], 0, 47, 42]]], "end_time": 0, "visited": 0, "total_needSend": 93, "exe_time": 96, "mapto": 47}, "117": {"total_needReceive": 93, "input_links": [], "start_time": 0, "out_links": [[[111, 93, [], [[[15, "W"], [14, "W"], [13, "S"], [21, "S"], [29, "S"], [37, "S"], [45, "W"], [44, "W"], [43, "W"]]], 0, 15, 42]]], "end_time": 0, "visited": 0, "total_needSend": 93, "exe_time": 70, "mapto": 15}, "118": {"total_needReceive": 93, "input_links": [], "start_time": 0, "out_links": [[[111, 93, [], [[[11, "W"], [10, "S"], [18, "S"], [26, "S"], [34, "S"]]], 0, 11, 42]]], "end_time": 0, "visited": 0, "total_needSend": 93, "exe_time": 19, "mapto": 11}, "119": {"total_needReceive": 93, "input_links": [], "start_time": 0, "out_links": [[[111, 93, [], [[[43, "W"]]], 0, 43, 42]]], "end_time": 0, "visited": 0, "total_needSend": 93, "exe_time": 129, "mapto": 43}, "120": {"total_needReceive": 93, "input_links": [], "start_time": 0, "out_links": [[[289, 1, [], [[[60, "E"], [61, "N"], [53, "N"], [45, "N"]]], 0, 60, 37]]], "end_time": 0, "visited": 0, "total_needSend": 1, "exe_time": 28, "mapto": 60}, "121": {"total_needReceive": 1, "input_links": [], "start_time": 0, "out_links": [[[122, 93, [], [[[24, "E"], [25, "E"]]], 0, 24, 26]]], "end_time": 0, "visited": 0, "total_needSend": 93, "exe_time": 4, "mapto": 24}, "122": {"total_needReceive": 93, "input_links": [], "start_time": 0, "out_links": [[[124, 93, [], [[[26, "S"], [34, "S"], [42, "E"], [43, "E"]]], 0, 26, 44]], [[125, 93, [], [[[26, "E"], [27, "N"], [19, "E"], [20, "N"]]], 0, 26, 12]], [[126, 93, [], [[[26, "W"], [25, "W"], [24, "N"], [16, "N"]]], 0, 26, 8]], [[127, 93, [], [[[26, "S"], [34, "S"], [42, "W"], [41, "W"]]], 0, 26, 40]], [[128, 93, [], [[[26, "E"], [27, "E"], [28, "S"], [36, "S"]]], 0, 26, 44]], [[129, 93, [], [[[26, "E"], [27, "N"], [19, "E"], [20, "N"]]], 0, 26, 12]], [[130, 93, [], [[[26, "W"], [25, "W"], [24, "N"], [16, "N"]]], 0, 26, 8]], [[131, 93, [], [[[26, "W"], [25, "W"], [24, "S"], [32, "S"]]], 0, 26, 40]]], "end_time": 0, "visited": 0, "total_needSend": 744, "exe_time": 99, "mapto": 26}, "123": {"total_needReceive": 744, "input_links": [], "start_time": 0, "out_links": [[[132, 93, [], [[[34, "E"], [35, "E"], [36, "S"], [44, "S"]]], 0, 34, 52]]], "end_time": 0, "visited": 0, "total_needSend": 93, "exe_time": 287, "mapto": 34}, "124": {"total_needReceive": 93, "input_links": [], "start_time": 0, "out_links": [[[123, 93, [], [[[44, "N"], [36, "W"], [35, "W"]]], 0, 44, 34]]], "end_time": 0, "visited": 0, "total_needSend": 93, "exe_time": 368, "mapto": 44}, "125": {"total_needReceive": 93, "input_links": [], "start_time": 0, "out_links": [[[123, 93, [], [[[12, "W"], [11, "W"], [10, "S"], [18, "S"], [26, "S"]]], 0, 12, 34]]], "end_time": 0, "visited": 0, "total_needSend": 93, "exe_time": 13, "mapto": 12}, "126": {"total_needReceive": 93, "input_links": [], "start_time": 0, "out_links": [[[123, 93, [], [[[8, "S"], [16, "S"], [24, "E"], [25, "S"], [33, "E"]]], 0, 8, 34]]], "end_time": 0, "visited": 0, "total_needSend": 93, "exe_time": 10, "mapto": 8}, "127": {"total_needReceive": 93, "input_links": [], "start_time": 0, "out_links": [[[123, 93, [], [[[40, "N"], [32, "E"], [33, "E"]]], 0, 40, 34]]], "end_time": 0, "visited": 0, "total_needSend": 93, "exe_time": 71, "mapto": 40}, "128": {"total_needReceive": 93, "input_links": [], "start_time": 0, "out_links": [[[123, 93, [], [[[44, "N"], [36, "W"], [35, "W"]]], 0, 44, 34]]], "end_time": 0, "visited": 0, "total_needSend": 93, "exe_time": 165, "mapto": 44}, "129": {"total_needReceive": 93, "input_links": [], "start_time": 0, "out_links": [[[123, 93, [], [[[12, "W"], [11, "W"], [10, "S"], [18, "S"], [26, "S"]]], 0, 12, 34]]], "end_time": 0, "visited": 0, "total_needSend": 93, "exe_time": 137, "mapto": 12}, "130": {"total_needReceive": 93, "input_links": [], "start_time": 0, "out_links": [[[123, 93, [], [[[8, "E"], [9, "E"], [10, "S"], [18, "S"], [26, "S"]]], 0, 8, 34]]], "end_time": 0, "visited": 0, "total_needSend": 93, "exe_time": 81, "mapto": 8}, "131": {"total_needReceive": 93, "input_links": [], "start_time": 0, "out_links": [[[123, 93, [], [[[40, "N"], [32, "E"], [33, "E"]]], 0, 40, 34]]], "end_time": 0, "visited": 0, "total_needSend": 93, "exe_time": 25, "mapto": 40}, "132": {"total_needReceive": 93, "input_links": [], "start_time": 0, "out_links": [[[289, 1, [], [[[52, "N"], [44, "N"], [36, "E"]]], 0, 52, 37]]], "end_time": 0, "visited": 0, "total_needSend": 1, "exe_time": 17, "mapto": 52}, "133": {"total_needReceive": 1, "input_links": [], "start_time": 0, "out_links": [[[134, 93, [], [[[56, "E"], [57, "E"], [58, "N"], [50, "N"], [42, "N"], [34, "N"], [26, "N"]]], 0, 56, 18]]], "end_time": 0, "visited": 0, "total_needSend": 93, "exe_time": 163, "mapto": 56}, "134": {"total_needReceive": 93, "input_links": [], "start_time": 0, "out_links": [[[136, 93, [], [[[18, "E"], [19, "E"], [20, "S"], [28, "S"]]], 0, 18, 36]], [[137, 93, [], [[[18, "E"], [19, "E"], [20, "N"], [12, "N"]]], 0, 18, 4]], [[138, 93, [], [[[18, "W"], [17, "N"], [9, "W"], [8, "N"]]], 0, 18, 0]], [[139, 93, [], [[[18, "W"], [17, "W"], [16, "S"], [24, "S"]]], 0, 18, 32]], [[140, 93, [], [[[18, "E"], [19, "E"], [20, "S"], [28, "S"]]], 0, 18, 36]], [[141, 93, [], [[[18, "N"], [10, "N"], [2, "E"], [3, "E"]]], 0, 18, 4]], [[142, 93, [], [[[18, "W"], [17, "W"], [16, "N"], [8, "N"]]], 0, 18, 0]], [[143, 93, [], [[[18, "W"], [17, "W"], [16, "S"], [24, "S"]]], 0, 18, 32]]], "end_time": 0, "visited": 0, "total_needSend": 744, "exe_time": 30, "mapto": 18}, "135": {"total_needReceive": 744, "input_links": [], "start_time": 0, "out_links": [[[144, 93, [], [[[42, "S"], [50, "S"], [58, "E"], [59, "E"]]], 0, 42, 60]]], "end_time": 0, "visited": 0, "total_needSend": 93, "exe_time": 142, "mapto": 42}, "136": {"total_needReceive": 93, "input_links": [], "start_time": 0, "out_links": [[[135, 93, [], [[[36, "S"], [44, "W"], [43, "W"]]], 0, 36, 42]]], "end_time": 0, "visited": 0, "total_needSend": 93, "exe_time": 201, "mapto": 36}, "137": {"total_needReceive": 93, "input_links": [], "start_time": 0, "out_links": [[[135, 93, [], [[[4, "S"], [12, "W"], [11, "W"], [10, "S"], [18, "S"], [26, "S"], [34, "S"]]], 0, 4, 42]]], "end_time": 0, "visited": 0, "total_needSend": 93, "exe_time": 4, "mapto": 4}, "138": {"total_needReceive": 93, "input_links": [], "start_time": 0, "out_links": [[[135, 93, [], [[[0, "E"], [1, "E"], [2, "S"], [10, "S"], [18, "S"], [26, "S"], [34, "S"]]], 0, 0, 42]]], "end_time": 0, "visited": 0, "total_needSend": 93, "exe_time": 6, "mapto": 0}, "139": {"total_needReceive": 93, "input_links": [], "start_time": 0, "out_links": [[[135, 93, [], [[[32, "S"], [40, "E"], [41, "E"]]], 0, 32, 42]]], "end_time": 0, "visited": 0, "total_needSend": 93, "exe_time": 99, "mapto": 32}, "140": {"total_needReceive": 93, "input_links": [], "start_time": 0, "out_links": [[[135, 93, [], [[[36, "S"], [44, "W"], [43, "W"]]], 0, 36, 42]]], "end_time": 0, "visited": 0, "total_needSend": 93, "exe_time": 43, "mapto": 36}, "141": {"total_needReceive": 93, "input_links": [], "start_time": 0, "out_links": [[[135, 93, [], [[[4, "W"], [3, "W"], [2, "S"], [10, "S"], [18, "S"], [26, "S"], [34, "S"]]], 0, 4, 42]]], "end_time": 0, "visited": 0, "total_needSend": 93, "exe_time": 99, "mapto": 4}, "142": {"total_needReceive": 93, "input_links": [], "start_time": 0, "out_links": [[[135, 93, [], [[[0, "E"], [1, "S"], [9, "S"], [17, "S"], [25, "S"], [33, "S"], [41, "E"]]], 0, 0, 42]]], "end_time": 0, "visited": 0, "total_needSend": 93, "exe_time": 391, "mapto": 0}, "143": {"total_needReceive": 93, "input_links": [], "start_time": 0, "out_links": [[[135, 93, [], [[[32, "S"], [40, "E"], [41, "E"]]], 0, 32, 42]]], "end_time": 0, "visited": 0, "total_needSend": 93, "exe_time": 124, "mapto": 32}, "144": {"total_needReceive": 93, "input_links": [], "start_time": 0, "out_links": [[[289, 1, [], [[[60, "E"], [61, "N"], [53, "N"], [45, "N"]]], 0, 60, 37]]], "end_time": 0, "visited": 0, "total_needSend": 1, "exe_time": 22, "mapto": 60}, "145": {"total_needReceive": 1, "input_links": [], "start_time": 0, "out_links": [[[146, 93, [], [[[60, "W"], [59, "W"], [58, "N"], [50, "N"], [42, "N"], [34, "N"]]], 0, 60, 26]]], "end_time": 0, "visited": 0, "total_needSend": 93, "exe_time": 18, "mapto": 60}, "146": {"total_needReceive": 93, "input_links": [], "start_time": 0, "out_links": [[[148, 93, [], [[[26, "S"], [34, "S"], [42, "E"], [43, "E"]]], 0, 26, 44]], [[149, 93, [], [[[26, "N"], [18, "N"], [10, "E"], [11, "E"]]], 0, 26, 12]], [[150, 93, [], [[[26, "W"], [25, "N"], [17, "W"], [16, "N"]]], 0, 26, 8]], [[151, 93, [], [[[26, "W"], [25, "W"], [24, "S"], [32, "S"]]], 0, 26, 40]], [[152, 93, [], [[[26, "E"], [27, "E"], [28, "S"], [36, "S"]]], 0, 26, 44]], [[153, 93, [], [[[26, "N"], [18, "N"], [10, "E"], [11, "E"]]], 0, 26, 12]], [[154, 93, [], [[[26, "N"], [18, "W"], [17, "N"], [9, "W"]]], 0, 26, 8]], [[155, 93, [], [[[26, "W"], [25, "W"], [24, "S"], [32, "S"]]], 0, 26, 40]]], "end_time": 0, "visited": 0, "total_needSend": 744, "exe_time": 83, "mapto": 26}, "147": {"total_needReceive": 744, "input_links": [], "start_time": 0, "out_links": [[[156, 93, [], [[[27, "E"], [28, "E"], [29, "S"], [37, "S"]]], 0, 27, 45]]], "end_time": 0, "visited": 0, "total_needSend": 93, "exe_time": 261, "mapto": 27}, "148": {"total_needReceive": 93, "input_links": [], "start_time": 0, "out_links": [[[147, 93, [], [[[44, "W"], [43, "N"], [35, "N"]]], 0, 44, 27]]], "end_time": 0, "visited": 0, "total_needSend": 93, "exe_time": 5, "mapto": 44}, "149": {"total_needReceive": 93, "input_links": [], "start_time": 0, "out_links": [[[147, 93, [], [[[12, "W"], [11, "S"], [19, "S"]]], 0, 12, 27]]], "end_time": 0, "visited": 0, "total_needSend": 93, "exe_time": 21, "mapto": 12}, "150": {"total_needReceive": 93, "input_links": [], "start_time": 0, "out_links": [[[147, 93, [], [[[8, "E"], [9, "E"], [10, "E"], [11, "S"], [19, "S"]]], 0, 8, 27]]], "end_time": 0, "visited": 0, "total_needSend": 93, "exe_time": 18, "mapto": 8}, "151": {"total_needReceive": 93, "input_links": [], "start_time": 0, "out_links": [[[147, 93, [], [[[40, "E"], [41, "N"], [33, "N"], [25, "E"], [26, "E"]]], 0, 40, 27]]], "end_time": 0, "visited": 0, "total_needSend": 93, "exe_time": 225, "mapto": 40}, "152": {"total_needReceive": 93, "input_links": [], "start_time": 0, "out_links": [[[147, 93, [], [[[44, "W"], [43, "N"], [35, "N"]]], 0, 44, 27]]], "end_time": 0, "visited": 0, "total_needSend": 93, "exe_time": 105, "mapto": 44}, "153": {"total_needReceive": 93, "input_links": [], "start_time": 0, "out_links": [[[147, 93, [], [[[12, "W"], [11, "S"], [19, "S"]]], 0, 12, 27]]], "end_time": 0, "visited": 0, "total_needSend": 93, "exe_time": 52, "mapto": 12}, "154": {"total_needReceive": 93, "input_links": [], "start_time": 0, "out_links": [[[147, 93, [], [[[8, "E"], [9, "E"], [10, "E"], [11, "S"], [19, "S"]]], 0, 8, 27]]], "end_time": 0, "visited": 0, "total_needSend": 93, "exe_time": 104, "mapto": 8}, "155": {"total_needReceive": 93, "input_links": [], "start_time": 0, "out_links": [[[147, 93, [], [[[40, "N"], [32, "N"], [24, "E"], [25, "E"], [26, "E"]]], 0, 40, 27]]], "end_time": 0, "visited": 0, "total_needSend": 93, "exe_time": 73, "mapto": 40}, "156": {"total_needReceive": 93, "input_links": [], "start_time": 0, "out_links": [[[289, 1, [], [[[45, "N"]]], 0, 45, 37]]], "end_time": 0, "visited": 0, "total_needSend": 1, "exe_time": 167, "mapto": 45}, "157": {"total_needReceive": 1, "input_links": [], "start_time": 0, "out_links": [[[158, 93, [], [[[28, "N"], [20, "W"], [19, "W"]]], 0, 28, 18]]], "end_time": 0, "visited": 0, "total_needSend": 93, "exe_time": 117, "mapto": 28}, "158": {"total_needReceive": 93, "input_links": [], "start_time": 0, "out_links": [[[160, 93, [], [[[18, "E"], [19, "E"], [20, "S"], [28, "S"]]], 0, 18, 36]], [[161, 93, [], [[[18, "E"], [19, "E"], [20, "N"], [12, "N"]]], 0, 18, 4]], [[162, 93, [], [[[18, "N"], [10, "N"], [2, "W"], [1, "W"]]], 0, 18, 0]], [[163, 93, [], [[[18, "W"], [17, "W"], [16, "S"], [24, "S"]]], 0, 18, 32]], [[164, 93, [], [[[18, "E"], [19, "E"], [20, "S"], [28, "S"]]], 0, 18, 36]], [[165, 93, [], [[[18, "E"], [19, "E"], [20, "N"], [12, "N"]]], 0, 18, 4]], [[166, 93, [], [[[18, "W"], [17, "W"], [16, "N"], [8, "N"]]], 0, 18, 0]], [[167, 93, [], [[[18, "S"], [26, "S"], [34, "W"], [33, "W"]]], 0, 18, 32]]], "end_time": 0, "visited": 0, "total_needSend": 744, "exe_time": 94, "mapto": 18}, "159": {"total_needReceive": 744, "input_links": [], "start_time": 0, "out_links": [[[168, 93, [], [[[26, "S"], [34, "S"], [42, "E"], [43, "E"]]], 0, 26, 44]]], "end_time": 0, "visited": 0, "total_needSend": 93, "exe_time": 41, "mapto": 26}, "160": {"total_needReceive": 93, "input_links": [], "start_time": 0, "out_links": [[[159, 93, [], [[[36, "W"], [35, "W"], [34, "N"]]], 0, 36, 26]]], "end_time": 0, "visited": 0, "total_needSend": 93, "exe_time": 214, "mapto": 36}, "161": {"total_needReceive": 93, "input_links": [], "start_time": 0, "out_links": [[[159, 93, [], [[[4, "W"], [3, "W"], [2, "S"], [10, "S"], [18, "S"]]], 0, 4, 26]]], "end_time": 0, "visited": 0, "total_needSend": 93, "exe_time": 6, "mapto": 4}, "162": {"total_needReceive": 93, "input_links": [], "start_time": 0, "out_links": [[[159, 93, [], [[[0, "E"], [1, "S"], [9, "S"], [17, "S"], [25, "E"]]], 0, 0, 26]]], "end_time": 0, "visited": 0, "total_needSend": 93, "exe_time": 6, "mapto": 0}, "163": {"total_needReceive": 93, "input_links": [], "start_time": 0, "out_links": [[[159, 93, [], [[[32, "N"], [24, "E"], [25, "E"]]], 0, 32, 26]]], "end_time": 0, "visited": 0, "total_needSend": 93, "exe_time": 21, "mapto": 32}, "164": {"total_needReceive": 93, "input_links": [], "start_time": 0, "out_links": [[[159, 93, [], [[[36, "N"], [28, "W"], [27, "W"]]], 0, 36, 26]]], "end_time": 0, "visited": 0, "total_needSend": 93, "exe_time": 39, "mapto": 36}, "165": {"total_needReceive": 93, "input_links": [], "start_time": 0, "out_links": [[[159, 93, [], [[[4, "S"], [12, "S"], [20, "S"], [28, "W"], [27, "W"]]], 0, 4, 26]]], "end_time": 0, "visited": 0, "total_needSend": 93, "exe_time": 58, "mapto": 4}, "166": {"total_needReceive": 93, "input_links": [], "start_time": 0, "out_links": [[[159, 93, [], [[[0, "E"], [1, "S"], [9, "S"], [17, "S"], [25, "E"]]], 0, 0, 26]]], "end_time": 0, "visited": 0, "total_needSend": 93, "exe_time": 107, "mapto": 0}, "167": {"total_needReceive": 93, "input_links": [], "start_time": 0, "out_links": [[[159, 93, [], [[[32, "N"], [24, "E"], [25, "E"]]], 0, 32, 26]]], "end_time": 0, "visited": 0, "total_needSend": 93, "exe_time": 8, "mapto": 32}, "168": {"total_needReceive": 93, "input_links": [], "start_time": 0, "out_links": [[[289, 1, [], [[[44, "N"], [36, "E"]]], 0, 44, 37]]], "end_time": 0, "visited": 0, "total_needSend": 1, "exe_time": 85, "mapto": 44}, "169": {"total_needReceive": 1, "input_links": [], "start_time": 0, "out_links": [[[170, 93, [], [[[24, "S"], [32, "S"], [40, "E"], [41, "E"], [42, "E"], [43, "E"], [44, "E"]]], 0, 24, 45]]], "end_time": 0, "visited": 0, "total_needSend": 93, "exe_time": 10, "mapto": 24}, "170": {"total_needReceive": 93, "input_links": [], "start_time": 0, "out_links": [[[172, 93, [], [[[45, "S"], [53, "E"], [54, "S"], [62, "E"]]], 0, 45, 63]], [[173, 93, [], [[[45, "E"], [46, "E"], [47, "N"], [39, "N"]]], 0, 45, 31]], [[174, 93, [], [[[45, "W"], [44, "W"], [43, "N"], [35, "N"]]], 0, 45, 27]], [[175, 93, [], [[[45, "W"], [44, "S"], [52, "W"], [51, "S"]]], 0, 45, 59]], [[176, 93, [], [[[45, "S"], [53, "S"], [61, "E"], [62, "E"]]], 0, 45, 63]], [[177, 93, [], [[[45, "E"], [46, "E"], [47, "N"], [39, "N"]]], 0, 45, 31]], [[178, 93, [], [[[45, "N"], [37, "N"], [29, "W"], [28, "W"]]], 0, 45, 27]], [[179, 93, [], [[[45, "S"], [53, "S"], [61, "W"], [60, "W"]]], 0, 45, 59]]], "end_time": 0, "visited": 0, "total_needSend": 744, "exe_time": 16, "mapto": 45}, "171": {"total_needReceive": 744, "input_links": [], "start_time": 0, "out_links": [[[180, 93, [], [[[20, "E"], [21, "E"], [22, "S"], [30, "S"]]], 0, 20, 38]]], "end_time": 0, "visited": 0, "total_needSend": 93, "exe_time": 177, "mapto": 20}, "172": {"total_needReceive": 93, "input_links": [], "start_time": 0, "out_links": [[[171, 93, [], [[[63, "N"], [55, "W"], [54, "N"], [46, "N"], [38, "N"], [30, "N"], [22, "W"], [21, "W"]]], 0, 63, 20]]], "end_time": 0, "visited": 0, "total_needSend": 93, "exe_time": 29, "mapto": 63}, "173": {"total_needReceive": 93, "input_links": [], "start_time": 0, "out_links": [[[171, 93, [], [[[31, "N"], [23, "W"], [22, "W"], [21, "W"]]], 0, 31, 20]]], "end_time": 0, "visited": 0, "total_needSend": 93, "exe_time": 17, "mapto": 31}, "174": {"total_needReceive": 93, "input_links": [], "start_time": 0, "out_links": [[[171, 93, [], [[[27, "N"], [19, "E"]]], 0, 27, 20]]], "end_time": 0, "visited": 0, "total_needSend": 93, "exe_time": 1, "mapto": 27}, "175": {"total_needReceive": 93, "input_links": [], "start_time": 0, "out_links": [[[171, 93, [], [[[59, "E"], [60, "N"], [52, "N"], [44, "N"], [36, "N"], [28, "N"]]], 0, 59, 20]]], "end_time": 0, "visited": 0, "total_needSend": 93, "exe_time": 95, "mapto": 59}, "176": {"total_needReceive": 93, "input_links": [], "start_time": 0, "out_links": [[[171, 93, [], [[[63, "N"], [55, "N"], [47, "N"], [39, "N"], [31, "N"], [23, "W"], [22, "W"], [21, "W"]]], 0, 63, 20]]], "end_time": 0, "visited": 0, "total_needSend": 93, "exe_time": 117, "mapto": 63}, "177": {"total_needReceive": 93, "input_links": [], "start_time": 0, "out_links": [[[171, 93, [], [[[31, "N"], [23, "W"], [22, "W"], [21, "W"]]], 0, 31, 20]]], "end_time": 0, "visited": 0, "total_needSend": 93, "exe_time": 162, "mapto": 31}, "178": {"total_needReceive": 93, "input_links": [], "start_time": 0, "out_links": [[[171, 93, [], [[[27, "N"], [19, "E"]]], 0, 27, 20]]], "end_time": 0, "visited": 0, "total_needSend": 93, "exe_time": 41, "mapto": 27}, "179": {"total_needReceive": 93, "input_links": [], "start_time": 0, "out_links": [[[171, 93, [], [[[59, "E"], [60, "N"], [52, "N"], [44, "N"], [36, "N"], [28, "N"]]], 0, 59, 20]]], "end_time": 0, "visited": 0, "total_needSend": 93, "exe_time": 11, "mapto": 59}, "180": {"total_needReceive": 93, "input_links": [], "start_time": 0, "out_links": [[[289, 1, [], [[[38, "W"]]], 0, 38, 37]]], "end_time": 0, "visited": 0, "total_needSend": 1, "exe_time": 95, "mapto": 38}, "181": {"total_needReceive": 1, "input_links": [], "start_time": 0, "out_links": [[[182, 93, [], [[[56, "E"], [57, "N"], [49, "E"], [50, "E"], [51, "N"], [43, "N"], [35, "N"]]], 0, 56, 27]]], "end_time": 0, "visited": 0, "total_needSend": 93, "exe_time": 90, "mapto": 56}, "182": {"total_needReceive": 93, "input_links": [], "start_time": 0, "out_links": [[[184, 93, [], [[[27, "E"], [28, "E"], [29, "S"], [37, "S"]]], 0, 27, 45]], [[185, 93, [], [[[27, "N"], [19, "N"], [11, "E"], [12, "E"]]], 0, 27, 13]], [[186, 93, [], [[[27, "N"], [19, "N"], [11, "W"], [10, "W"]]], 0, 27, 9]], [[187, 93, [], [[[27, "S"], [35, "S"], [43, "W"], [42, "W"]]], 0, 27, 41]], [[188, 93, [], [[[27, "S"], [35, "S"], [43, "E"], [44, "E"]]], 0, 27, 45]], [[189, 93, [], [[[27, "N"], [19, "N"], [11, "E"], [12, "E"]]], 0, 27, 13]], [[190, 93, [], [[[27, "N"], [19, "N"], [11, "W"], [10, "W"]]], 0, 27, 9]], [[191, 93, [], [[[27, "S"], [35, "S"], [43, "W"], [42, "W"]]], 0, 27, 41]]], "end_time": 0, "visited": 0, "total_needSend": 744, "exe_time": 29, "mapto": 27}, "183": {"total_needReceive": 744, "input_links": [], "start_time": 0, "out_links": [[[192, 93, [], [[[18, "E"], [19, "E"], [20, "S"], [28, "S"]]], 0, 18, 36]]], "end_time": 0, "visited": 0, "total_needSend": 93, "exe_time": 1214, "mapto": 18}, "184": {"total_needReceive": 93, "input_links": [], "start_time": 0, "out_links": [[[183, 93, [], [[[45, "W"], [44, "W"], [43, "W"], [42, "N"], [34, "N"], [26, "N"]]], 0, 45, 18]]], "end_time": 0, "visited": 0, "total_needSend": 93, "exe_time": 14, "mapto": 45}, "185": {"total_needReceive": 93, "input_links": [], "start_time": 0, "out_links": [[[183, 93, [], [[[13, "W"], [12, "W"], [11, "W"], [10, "S"]]], 0, 13, 18]]], "end_time": 0, "visited": 0, "total_needSend": 93, "exe_time": 28, "mapto": 13}, "186": {"total_needReceive": 93, "input_links": [], "start_time": 0, "out_links": [[[183, 93, [], [[[9, "E"], [10, "S"]]], 0, 9, 18]]], "end_time": 0, "visited": 0, "total_needSend": 93, "exe_time": 1, "mapto": 9}, "187": {"total_needReceive": 93, "input_links": [], "start_time": 0, "out_links": [[[183, 93, [], [[[41, "N"], [33, "N"], [25, "N"], [17, "E"]]], 0, 41, 18]]], "end_time": 0, "visited": 0, "total_needSend": 93, "exe_time": 110, "mapto": 41}, "188": {"total_needReceive": 93, "input_links": [], "start_time": 0, "out_links": [[[183, 93, [], [[[45, "W"], [44, "W"], [43, "W"], [42, "N"], [34, "N"], [26, "N"]]], 0, 45, 18]]], "end_time": 0, "visited": 0, "total_needSend": 93, "exe_time": 17, "mapto": 45}, "189": {"total_needReceive": 93, "input_links": [], "start_time": 0, "out_links": [[[183, 93, [], [[[13, "W"], [12, "W"], [11, "W"], [10, "S"]]], 0, 13, 18]]], "end_time": 0, "visited": 0, "total_needSend": 93, "exe_time": 165, "mapto": 13}, "190": {"total_needReceive": 93, "input_links": [], "start_time": 0, "out_links": [[[183, 93, [], [[[9, "S"], [17, "E"]]], 0, 9, 18]]], "end_time": 0, "visited": 0, "total_needSend": 93, "exe_time": 87, "mapto": 9}, "191": {"total_needReceive": 93, "input_links": [], "start_time": 0, "out_links": [[[183, 93, [], [[[41, "N"], [33, "N"], [25, "N"], [17, "E"]]], 0, 41, 18]]], "end_time": 0, "visited": 0, "total_needSend": 93, "exe_time": 9, "mapto": 41}, "192": {"total_needReceive": 93, "input_links": [], "start_time": 0, "out_links": [[[289, 1, [], [[[36, "E"]]], 0, 36, 37]]], "end_time": 0, "visited": 0, "total_needSend": 1, "exe_time": 257, "mapto": 36}, "193": {"total_needReceive": 1, "input_links": [], "start_time": 0, "out_links": [[[194, 93, [], [[[60, "N"], [52, "N"], [44, "W"], [43, "W"]]], 0, 60, 42]]], "end_time": 0, "visited": 0, "total_needSend": 93, "exe_time": 23, "mapto": 60}, "194": {"total_needReceive": 93, "input_links": [], "start_time": 0, "out_links": [[[196, 93, [], [[[42, "S"], [50, "S"], [58, "E"], [59, "E"]]], 0, 42, 60]], [[197, 93, [], [[[42, "N"], [34, "E"], [35, "E"], [36, "N"]]], 0, 42, 28]], [[198, 93, [], [[[42, "W"], [41, "W"], [40, "N"], [32, "N"]]], 0, 42, 24]], [[199, 93, [], [[[42, "S"], [50, "S"], [58, "W"], [57, "W"]]], 0, 42, 56]], [[200, 93, [], [[[42, "S"], [50, "S"], [58, "E"], [59, "E"]]], 0, 42, 60]], [[201, 93, [], [[[42, "E"], [43, "E"], [44, "N"], [36, "N"]]], 0, 42, 28]], [[202, 93, [], [[[42, "W"], [41, "W"], [40, "N"], [32, "N"]]], 0, 42, 24]], [[203, 93, [], [[[42, "S"], [50, "W"], [49, "S"], [57, "W"]]], 0, 42, 56]]], "end_time": 0, "visited": 0, "total_needSend": 744, "exe_time": 33, "mapto": 42}, "195": {"total_needReceive": 744, "input_links": [], "start_time": 0, "out_links": [[[204, 93, [], [[[28, "E"], [29, "E"], [30, "S"], [38, "S"]]], 0, 28, 46]]], "end_time": 0, "visited": 0, "total_needSend": 93, "exe_time": 135, "mapto": 28}, "196": {"total_needReceive": 93, "input_links": [], "start_time": 0, "out_links": [[[195, 93, [], [[[60, "N"], [52, "N"], [44, "N"], [36, "N"]]], 0, 60, 28]]], "end_time": 0, "visited": 0, "total_needSend": 93, "exe_time": 227, "mapto": 60}, "197": {"total_needReceive": 93, "input_links": [], "start_time": 0, "out_links": [[[195, 93, [], [[]], 0, 28, 28]]], "end_time": 0, "visited": 0, "total_needSend": 93, "exe_time": 25, "mapto": 28}, "198": {"total_needReceive": 93, "input_links": [], "start_time": 0, "out_links": [[[195, 93, [], [[[24, "E"], [25, "E"], [26, "E"], [27, "E"]]], 0, 24, 28]]], "end_time": 0, "visited": 0, "total_needSend": 93, "exe_time": 17, "mapto": 24}, "199": {"total_needReceive": 93, "input_links": [], "start_time": 0, "out_links": [[[195, 93, [], [[[56, "N"], [48, "E"], [49, "N"], [41, "N"], [33, "N"], [25, "E"], [26, "E"], [27, "E"]]], 0, 56, 28]]], "end_time": 0, "visited": 0, "total_needSend": 93, "exe_time": 19, "mapto": 56}, "200": {"total_needReceive": 93, "input_links": [], "start_time": 0, "out_links": [[[195, 93, [], [[[60, "N"], [52, "N"], [44, "N"], [36, "N"]]], 0, 60, 28]]], "end_time": 0, "visited": 0, "total_needSend": 93, "exe_time": 143, "mapto": 60}, "201": {"total_needReceive": 93, "input_links": [], "start_time": 0, "out_links": [[[195, 93, [], [[]], 0, 28, 28]]], "end_time": 0, "visited": 0, "total_needSend": 93, "exe_time": 84, "mapto": 28}, "202": {"total_needReceive": 93, "input_links": [], "start_time": 0, "out_links": [[[195, 93, [], [[[24, "E"], [25, "E"], [26, "E"], [27, "E"]]], 0, 24, 28]]], "end_time": 0, "visited": 0, "total_needSend": 93, "exe_time": 24, "mapto": 24}, "203": {"total_needReceive": 93, "input_links": [], "start_time": 0, "out_links": [[[195, 93, [], [[[56, "N"], [48, "E"], [49, "N"], [41, "N"], [33, "N"], [25, "E"], [26, "E"], [27, "E"]]], 0, 56, 28]]], "end_time": 0, "visited": 0, "total_needSend": 93, "exe_time": 132, "mapto": 56}, "204": {"total_needReceive": 93, "input_links": [], "start_time": 0, "out_links": [[[289, 1, [], [[[46, "N"], [38, "W"]]], 0, 46, 37]]], "end_time": 0, "visited": 0, "total_needSend": 1, "exe_time": 21, "mapto": 46}, "205": {"total_needReceive": 1, "input_links": [], "start_time": 0, "out_links": [[[206, 93, [], [[[28, "S"], [36, "W"], [35, "W"]]], 0, 28, 34]]], "end_time": 0, "visited": 0, "total_needSend": 93, "exe_time": 33, "mapto": 28}, "206": {"total_needReceive": 93, "input_links": [], "start_time": 0, "out_links": [[[208, 93, [], [[[34, "E"], [35, "E"], [36, "S"], [44, "S"]]], 0, 34, 52]], [[209, 93, [], [[[34, "E"], [35, "E"], [36, "N"], [28, "N"]]], 0, 34, 20]], [[210, 93, [], [[[34, "W"], [33, "W"], [32, "N"], [24, "N"]]], 0, 34, 16]], [[211, 93, [], [[[34, "W"], [33, "S"], [41, "S"], [49, "W"]]], 0, 34, 48]], [[212, 93, [], [[[34, "E"], [35, "E"], [36, "S"], [44, "S"]]], 0, 34, 52]], [[213, 93, [], [[[34, "N"], [26, "N"], [18, "E"], [19, "E"]]], 0, 34, 20]], [[214, 93, [], [[[34, "W"], [33, "W"], [32, "N"], [24, "N"]]], 0, 34, 16]], [[215, 93, [], [[[34, "W"], [33, "W"], [32, "S"], [40, "S"]]], 0, 34, 48]]], "end_time": 0, "visited": 0, "total_needSend": 744, "exe_time": 64, "mapto": 34}, "207": {"total_needReceive": 744, "input_links": [], "start_time": 0, "out_links": [[[216, 93, [], [[[18, "E"], [19, "E"], [20, "S"], [28, "S"]]], 0, 18, 36]]], "end_time": 0, "visited": 0, "total_needSend": 93, "exe_time": 323, "mapto": 18}, "208": {"total_needReceive": 93, "input_links": [], "start_time": 0, "out_links": [[[207, 93, [], [[[52, "W"], [51, "W"], [50, "N"], [42, "N"], [34, "N"], [26, "N"]]], 0, 52, 18]]], "end_time": 0, "visited": 0, "total_needSend": 93, "exe_time": 47, "mapto": 52}, "209": {"total_needReceive": 93, "input_links": [], "start_time": 0, "out_links": [[[207, 93, [], [[[20, "W"], [19, "W"]]], 0, 20, 18]]], "end_time": 0, "visited": 0, "total_needSend": 93, "exe_time": 14, "mapto": 20}, "210": {"total_needReceive": 93, "input_links": [], "start_time": 0, "out_links": [[[207, 93, [], [[[16, "E"], [17, "E"]]], 0, 16, 18]]], "end_time": 0, "visited": 0, "total_needSend": 93, "exe_time": 0, "mapto": 16}, "211": {"total_needReceive": 93, "input_links": [], "start_time": 0, "out_links": [[[207, 93, [], [[[48, "N"], [40, "E"], [41, "E"], [42, "N"], [34, "N"], [26, "N"]]], 0, 48, 18]]], "end_time": 0, "visited": 0, "total_needSend": 93, "exe_time": 42, "mapto": 48}, "212": {"total_needReceive": 93, "input_links": [], "start_time": 0, "out_links": [[[207, 93, [], [[[52, "W"], [51, "W"], [50, "N"], [42, "N"], [34, "N"], [26, "N"]]], 0, 52, 18]]], "end_time": 0, "visited": 0, "total_needSend": 93, "exe_time": 146, "mapto": 52}, "213": {"total_needReceive": 93, "input_links": [], "start_time": 0, "out_links": [[[207, 93, [], [[[20, "W"], [19, "W"]]], 0, 20, 18]]], "end_time": 0, "visited": 0, "total_needSend": 93, "exe_time": 109, "mapto": 20}, "214": {"total_needReceive": 93, "input_links": [], "start_time": 0, "out_links": [[[207, 93, [], [[[16, "E"], [17, "E"]]], 0, 16, 18]]], "end_time": 0, "visited": 0, "total_needSend": 93, "exe_time": 59, "mapto": 16}, "215": {"total_needReceive": 93, "input_links": [], "start_time": 0, "out_links": [[[207, 93, [], [[[48, "E"], [49, "N"], [41, "N"], [33, "N"], [25, "N"], [17, "E"]]], 0, 48, 18]]], "end_time": 0, "visited": 0, "total_needSend": 93, "exe_time": 254, "mapto": 48}, "216": {"total_needReceive": 93, "input_links": [], "start_time": 0, "out_links": [[[289, 1, [], [[[36, "E"]]], 0, 36, 37]]], "end_time": 0, "visited": 0, "total_needSend": 1, "exe_time": 67, "mapto": 36}, "217": {"total_needReceive": 1, "input_links": [], "start_time": 0, "out_links": [[[218, 93, [], [[[24, "S"], [32, "S"], [40, "E"], [41, "E"]]], 0, 24, 42]]], "end_time": 0, "visited": 0, "total_needSend": 93, "exe_time": 136, "mapto": 24}, "218": {"total_needReceive": 93, "input_links": [], "start_time": 0, "out_links": [[[220, 93, [], [[[42, "S"], [50, "S"], [58, "E"], [59, "E"]]], 0, 42, 60]], [[221, 93, [], [[[42, "N"], [34, "N"], [26, "E"], [27, "E"]]], 0, 42, 28]], [[222, 93, [], [[[42, "N"], [34, "W"], [33, "N"], [25, "W"]]], 0, 42, 24]], [[223, 93, [], [[[42, "S"], [50, "W"], [49, "S"], [57, "W"]]], 0, 42, 56]], [[224, 93, [], [[[42, "E"], [43, "E"], [44, "S"], [52, "S"]]], 0, 42, 60]], [[225, 93, [], [[[42, "N"], [34, "N"], [26, "E"], [27, "E"]]], 0, 42, 28]], [[226, 93, [], [[[42, "W"], [41, "W"], [40, "N"], [32, "N"]]], 0, 42, 24]], [[227, 93, [], [[[42, "W"], [41, "W"], [40, "S"], [48, "S"]]], 0, 42, 56]]], "end_time": 0, "visited": 0, "total_needSend": 744, "exe_time": 102, "mapto": 42}, "219": {"total_needReceive": 744, "input_links": [], "start_time": 0, "out_links": [[[228, 93, [], [[[35, "S"], [43, "S"], [51, "E"], [52, "E"]]], 0, 35, 53]]], "end_time": 0, "visited": 0, "total_needSend": 93, "exe_time": 27, "mapto": 35}, "220": {"total_needReceive": 93, "input_links": [], "start_time": 0, "out_links": [[[219, 93, [], [[[60, "W"], [59, "N"], [51, "N"], [43, "N"]]], 0, 60, 35]]], "end_time": 0, "visited": 0, "total_needSend": 93, "exe_time": 270, "mapto": 60}, "221": {"total_needReceive": 93, "input_links": [], "start_time": 0, "out_links": [[[219, 93, [], [[[28, "S"], [36, "W"]]], 0, 28, 35]]], "end_time": 0, "visited": 0, "total_needSend": 93, "exe_time": 3, "mapto": 28}, "222": {"total_needReceive": 93, "input_links": [], "start_time": 0, "out_links": [[[219, 93, [], [[[24, "E"], [25, "S"], [33, "E"], [34, "E"]]], 0, 24, 35]]], "end_time": 0, "visited": 0, "total_needSend": 93, "exe_time": 15, "mapto": 24}, "223": {"total_needReceive": 93, "input_links": [], "start_time": 0, "out_links": [[[219, 93, [], [[[56, "E"], [57, "E"], [58, "E"], [59, "N"], [51, "N"], [43, "N"]]], 0, 56, 35]]], "end_time": 0, "visited": 0, "total_needSend": 93, "exe_time": 148, "mapto": 56}, "224": {"total_needReceive": 93, "input_links": [], "start_time": 0, "out_links": [[[219, 93, [], [[[60, "W"], [59, "N"], [51, "N"], [43, "N"]]], 0, 60, 35]]], "end_time": 0, "visited": 0, "total_needSend": 93, "exe_time": 14, "mapto": 60}, "225": {"total_needReceive": 93, "input_links": [], "start_time": 0, "out_links": [[[219, 93, [], [[[28, "W"], [27, "S"]]], 0, 28, 35]]], "end_time": 0, "visited": 0, "total_needSend": 93, "exe_time": 146, "mapto": 28}, "226": {"total_needReceive": 93, "input_links": [], "start_time": 0, "out_links": [[[219, 93, [], [[[24, "E"], [25, "S"], [33, "E"], [34, "E"]]], 0, 24, 35]]], "end_time": 0, "visited": 0, "total_needSend": 93, "exe_time": 45, "mapto": 24}, "227": {"total_needReceive": 93, "input_links": [], "start_time": 0, "out_links": [[[219, 93, [], [[[56, "E"], [57, "E"], [58, "N"], [50, "N"], [42, "N"], [34, "E"]]], 0, 56, 35]]], "end_time": 0, "visited": 0, "total_needSend": 93, "exe_time": 7, "mapto": 56}, "228": {"total_needReceive": 93, "input_links": [], "start_time": 0, "out_links": [[[289, 1, [], [[[53, "N"], [45, "N"]]], 0, 53, 37]]], "end_time": 0, "visited": 0, "total_needSend": 1, "exe_time": 74, "mapto": 53}, "229": {"total_needReceive": 1, "input_links": [], "start_time": 0, "out_links": [[[230, 93, [], [[[56, "N"], [48, "E"], [49, "N"], [41, "N"], [33, "N"], [25, "N"], [17, "E"], [18, "E"]]], 0, 56, 19]]], "end_time": 0, "visited": 0, "total_needSend": 93, "exe_time": 136, "mapto": 56}, "230": {"total_needReceive": 93, "input_links": [], "start_time": 0, "out_links": [[[232, 93, [], [[[19, "S"], [27, "S"], [35, "E"], [36, "E"]]], 0, 19, 37]], [[233, 93, [], [[[19, "N"], [11, "N"], [3, "E"], [4, "E"]]], 0, 19, 5]], [[234, 93, [], [[[19, "W"], [18, "W"], [17, "N"], [9, "N"]]], 0, 19, 1]], [[235, 93, [], [[[19, "S"], [27, "S"], [35, "W"], [34, "W"]]], 0, 19, 33]], [[236, 93, [], [[[19, "S"], [27, "S"], [35, "E"], [36, "E"]]], 0, 19, 37]], [[237, 93, [], [[[19, "N"], [11, "N"], [3, "E"], [4, "E"]]], 0, 19, 5]], [[238, 93, [], [[[19, "W"], [18, "W"], [17, "N"], [9, "N"]]], 0, 19, 1]], [[239, 93, [], [[[19, "S"], [27, "S"], [35, "W"], [34, "W"]]], 0, 19, 33]]], "end_time": 0, "visited": 0, "total_needSend": 744, "exe_time": 45, "mapto": 19}, "231": {"total_needReceive": 744, "input_links": [], "start_time": 0, "out_links": [[[240, 93, [], [[[45, "E"], [46, "E"], [47, "S"], [55, "S"]]], 0, 45, 63]]], "end_time": 0, "visited": 0, "total_needSend": 93, "exe_time": 151, "mapto": 45}, "232": {"total_needReceive": 93, "input_links": [], "start_time": 0, "out_links": [[[231, 93, [], [[[37, "S"]]], 0, 37, 45]]], "end_time": 0, "visited": 0, "total_needSend": 93, "exe_time": 21, "mapto": 37}, "233": {"total_needReceive": 93, "input_links": [], "start_time": 0, "out_links": [[[231, 93, [], [[[5, "S"], [13, "S"], [21, "S"], [29, "S"], [37, "S"]]], 0, 5, 45]]], "end_time": 0, "visited": 0, "total_needSend": 93, "exe_time": 15, "mapto": 5}, "234": {"total_needReceive": 93, "input_links": [], "start_time": 0, "out_links": [[[231, 93, [], [[[1, "E"], [2, "E"], [3, "E"], [4, "E"], [5, "S"], [13, "S"], [21, "S"], [29, "S"], [37, "S"]]], 0, 1, 45]]], "end_time": 0, "visited": 0, "total_needSend": 93, "exe_time": 4, "mapto": 1}, "235": {"total_needReceive": 93, "input_links": [], "start_time": 0, "out_links": [[[231, 93, [], [[[33, "S"], [41, "E"], [42, "E"], [43, "E"], [44, "E"]]], 0, 33, 45]]], "end_time": 0, "visited": 0, "total_needSend": 93, "exe_time": 67, "mapto": 33}, "236": {"total_needReceive": 93, "input_links": [], "start_time": 0, "out_links": [[[231, 93, [], [[[37, "S"]]], 0, 37, 45]]], "end_time": 0, "visited": 0, "total_needSend": 93, "exe_time": 56, "mapto": 37}, "237": {"total_needReceive": 93, "input_links": [], "start_time": 0, "out_links": [[[231, 93, [], [[[5, "S"], [13, "S"], [21, "S"], [29, "S"], [37, "S"]]], 0, 5, 45]]], "end_time": 0, "visited": 0, "total_needSend": 93, "exe_time": 60, "mapto": 5}, "238": {"total_needReceive": 93, "input_links": [], "start_time": 0, "out_links": [[[231, 93, [], [[[1, "E"], [2, "E"], [3, "E"], [4, "E"], [5, "S"], [13, "S"], [21, "S"], [29, "S"], [37, "S"]]], 0, 1, 45]]], "end_time": 0, "visited": 0, "total_needSend": 93, "exe_time": 49, "mapto": 1}, "239": {"total_needReceive": 93, "input_links": [], "start_time": 0, "out_links": [[[231, 93, [], [[[33, "S"], [41, "E"], [42, "E"], [43, "E"], [44, "E"]]], 0, 33, 45]]], "end_time": 0, "visited": 0, "total_needSend": 93, "exe_time": 55, "mapto": 33}, "240": {"total_needReceive": 93, "input_links": [], "start_time": 0, "out_links": [[[289, 1, [], [[[63, "W"], [62, "W"], [61, "N"], [53, "N"], [45, "N"]]], 0, 63, 37]]], "end_time": 0, "visited": 0, "total_needSend": 1, "exe_time": 32, "mapto": 63}, "241": {"total_needReceive": 1, "input_links": [], "start_time": 0, "out_links": [[[242, 93, [], [[[60, "N"], [52, "N"], [44, "N"], [36, "N"], [28, "N"]]], 0, 60, 20]]], "end_time": 0, "visited": 0, "total_needSend": 93, "exe_time": 10, "mapto": 60}, "242": {"total_needReceive": 93, "input_links": [], "start_time": 0, "out_links": [[[244, 93, [], [[[20, "E"], [21, "E"], [22, "S"], [30, "S"]]], 0, 20, 38]], [[245, 93, [], [[[20, "N"], [12, "E"], [13, "N"], [5, "E"]]], 0, 20, 6]], [[246, 93, [], [[[20, "W"], [19, "W"], [18, "N"], [10, "N"]]], 0, 20, 2]], [[247, 93, [], [[[20, "S"], [28, "W"], [27, "W"], [26, "S"]]], 0, 20, 34]], [[248, 93, [], [[[20, "E"], [21, "E"], [22, "S"], [30, "S"]]], 0, 20, 38]], [[249, 93, [], [[[20, "N"], [12, "N"], [4, "E"], [5, "E"]]], 0, 20, 6]], [[250, 93, [], [[[20, "W"], [19, "W"], [18, "N"], [10, "N"]]], 0, 20, 2]], [[251, 93, [], [[[20, "S"], [28, "S"], [36, "W"], [35, "W"]]], 0, 20, 34]]], "end_time": 0, "visited": 0, "total_needSend": 744, "exe_time": 8, "mapto": 20}, "243": {"total_needReceive": 744, "input_links": [], "start_time": 0, "out_links": [[[252, 93, [], [[[34, "S"], [42, "S"], [50, "E"], [51, "E"]]], 0, 34, 52]]], "end_time": 0, "visited": 0, "total_needSend": 93, "exe_time": 136, "mapto": 34}, "244": {"total_needReceive": 93, "input_links": [], "start_time": 0, "out_links": [[[243, 93, [], [[[38, "W"], [37, "W"], [36, "W"], [35, "W"]]], 0, 38, 34]]], "end_time": 0, "visited": 0, "total_needSend": 93, "exe_time": 78, "mapto": 38}, "245": {"total_needReceive": 93, "input_links": [], "start_time": 0, "out_links": [[[243, 93, [], [[[6, "S"], [14, "S"], [22, "S"], [30, "S"], [38, "W"], [37, "W"], [36, "W"], [35, "W"]]], 0, 6, 34]]], "end_time": 0, "visited": 0, "total_needSend": 93, "exe_time": 10, "mapto": 6}, "246": {"total_needReceive": 93, "input_links": [], "start_time": 0, "out_links": [[[243, 93, [], [[[2, "S"], [10, "S"], [18, "S"], [26, "S"]]], 0, 2, 34]]], "end_time": 0, "visited": 0, "total_needSend": 93, "exe_time": 18, "mapto": 2}, "247": {"total_needReceive": 93, "input_links": [], "start_time": 0, "out_links": [[[243, 93, [], [[]], 0, 34, 34]]], "end_time": 0, "visited": 0, "total_needSend": 93, "exe_time": 35, "mapto": 34}, "248": {"total_needReceive": 93, "input_links": [], "start_time": 0, "out_links": [[[243, 93, [], [[[38, "W"], [37, "W"], [36, "W"], [35, "W"]]], 0, 38, 34]]], "end_time": 0, "visited": 0, "total_needSend": 93, "exe_time": 337, "mapto": 38}, "249": {"total_needReceive": 93, "input_links": [], "start_time": 0, "out_links": [[[243, 93, [], [[[6, "W"], [5, "W"], [4, "W"], [3, "W"], [2, "S"], [10, "S"], [18, "S"], [26, "S"]]], 0, 6, 34]]], "end_time": 0, "visited": 0, "total_needSend": 93, "exe_time": 102, "mapto": 6}, "250": {"total_needReceive": 93, "input_links": [], "start_time": 0, "out_links": [[[243, 93, [], [[[2, "S"], [10, "S"], [18, "S"], [26, "S"]]], 0, 2, 34]]], "end_time": 0, "visited": 0, "total_needSend": 93, "exe_time": 107, "mapto": 2}, "251": {"total_needReceive": 93, "input_links": [], "start_time": 0, "out_links": [[[243, 93, [], [[]], 0, 34, 34]]], "end_time": 0, "visited": 0, "total_needSend": 93, "exe_time": 95, "mapto": 34}, "252": {"total_needReceive": 93, "input_links": [], "start_time": 0, "out_links": [[[289, 1, [], [[[52, "N"], [44, "N"], [36, "E"]]], 0, 52, 37]]], "end_time": 0, "visited": 0, "total_needSend": 1, "exe_time": 207, "mapto": 52}, "253": {"total_needReceive": 1, "input_links": [], "start_time": 0, "out_links": [[[254, 93, [], [[[28, "S"], [36, "W"], [35, "W"]]], 0, 28, 34]]], "end_time": 0, "visited": 0, "total_needSend": 93, "exe_time": 142, "mapto": 28}, "254": {"total_needReceive": 93, "input_links": [], "start_time": 0, "out_links": [[[256, 93, [], [[[34, "S"], [42, "S"], [50, "E"], [51, "E"]]], 0, 34, 52]], [[257, 93, [], [[[34, "E"], [35, "E"], [36, "N"], [28, "N"]]], 0, 34, 20]], [[258, 93, [], [[[34, "W"], [33, "N"], [25, "W"], [24, "N"]]], 0, 34, 16]], [[259, 93, [], [[[34, "W"], [33, "S"], [41, "W"], [40, "S"]]], 0, 34, 48]], [[260, 93, [], [[[34, "S"], [42, "S"], [50, "E"], [51, "E"]]], 0, 34, 52]], [[261, 93, [], [[[34, "E"], [35, "E"], [36, "N"], [28, "N"]]], 0, 34, 20]], [[262, 93, [], [[[34, "W"], [33, "W"], [32, "N"], [24, "N"]]], 0, 34, 16]], [[263, 93, [], [[[34, "W"], [33, "W"], [32, "S"], [40, "S"]]], 0, 34, 48]]], "end_time": 0, "visited": 0, "total_needSend": 744, "exe_time": 113, "mapto": 34}, "255": {"total_needReceive": 744, "input_links": [], "start_time": 0, "out_links": [[[264, 93, [], [[[29, "E"], [30, "S"], [38, "E"], [39, "S"]]], 0, 29, 47]]], "end_time": 0, "visited": 0, "total_needSend": 93, "exe_time": 339, "mapto": 29}, "256": {"total_needReceive": 93, "input_links": [], "start_time": 0, "out_links": [[[255, 93, [], [[[52, "E"], [53, "N"], [45, "N"], [37, "N"]]], 0, 52, 29]]], "end_time": 0, "visited": 0, "total_needSend": 93, "exe_time": 152, "mapto": 52}, "257": {"total_needReceive": 93, "input_links": [], "start_time": 0, "out_links": [[[255, 93, [], [[[20, "E"], [21, "S"]]], 0, 20, 29]]], "end_time": 0, "visited": 0, "total_needSend": 93, "exe_time": 9, "mapto": 20}, "258": {"total_needReceive": 93, "input_links": [], "start_time": 0, "out_links": [[[255, 93, [], [[[16, "S"], [24, "E"], [25, "E"], [26, "E"], [27, "E"], [28, "E"]]], 0, 16, 29]]], "end_time": 0, "visited": 0, "total_needSend": 93, "exe_time": 11, "mapto": 16}, "259": {"total_needReceive": 93, "input_links": [], "start_time": 0, "out_links": [[[255, 93, [], [[[48, "E"], [49, "E"], [50, "E"], [51, "E"], [52, "E"], [53, "N"], [45, "N"], [37, "N"]]], 0, 48, 29]]], "end_time": 0, "visited": 0, "total_needSend": 93, "exe_time": 12, "mapto": 48}, "260": {"total_needReceive": 93, "input_links": [], "start_time": 0, "out_links": [[[255, 93, [], [[[52, "E"], [53, "N"], [45, "N"], [37, "N"]]], 0, 52, 29]]], "end_time": 0, "visited": 0, "total_needSend": 93, "exe_time": 82, "mapto": 52}, "261": {"total_needReceive": 93, "input_links": [], "start_time": 0, "out_links": [[[255, 93, [], [[[20, "E"], [21, "S"]]], 0, 20, 29]]], "end_time": 0, "visited": 0, "total_needSend": 93, "exe_time": 94, "mapto": 20}, "262": {"total_needReceive": 93, "input_links": [], "start_time": 0, "out_links": [[[255, 93, [], [[[16, "E"], [17, "S"], [25, "E"], [26, "E"], [27, "E"], [28, "E"]]], 0, 16, 29]]], "end_time": 0, "visited": 0, "total_needSend": 93, "exe_time": 296, "mapto": 16}, "263": {"total_needReceive": 93, "input_links": [], "start_time": 0, "out_links": [[[255, 93, [], [[[48, "E"], [49, "E"], [50, "E"], [51, "E"], [52, "E"], [53, "N"], [45, "N"], [37, "N"]]], 0, 48, 29]]], "end_time": 0, "visited": 0, "total_needSend": 93, "exe_time": 44, "mapto": 48}, "264": {"total_needReceive": 93, "input_links": [], "start_time": 0, "out_links": [[[289, 1, [], [[[47, "W"], [46, "W"], [45, "N"]]], 0, 47, 37]]], "end_time": 0, "visited": 0, "total_needSend": 1, "exe_time": 104, "mapto": 47}, "265": {"total_needReceive": 1, "input_links": [], "start_time": 0, "out_links": [[[266, 93, [], [[[24, "S"], [32, "E"], [33, "E"], [34, "E"], [35, "E"], [36, "E"]]], 0, 24, 37]]], "end_time": 0, "visited": 0, "total_needSend": 93, "exe_time": 335, "mapto": 24}, "266": {"total_needReceive": 93, "input_links": [], "start_time": 0, "out_links": [[[268, 93, [], [[[37, "E"], [38, "E"], [39, "S"], [47, "S"]]], 0, 37, 55]], [[269, 93, [], [[[37, "N"], [29, "N"], [21, "E"], [22, "E"]]], 0, 37, 23]], [[270, 93, [], [[[37, "W"], [36, "W"], [35, "N"], [27, "N"]]], 0, 37, 19]], [[271, 93, [], [[[37, "W"], [36, "W"], [35, "S"], [43, "S"]]], 0, 37, 51]], [[272, 93, [], [[[37, "E"], [38, "E"], [39, "S"], [47, "S"]]], 0, 37, 55]], [[273, 93, [], [[[37, "E"], [38, "E"], [39, "N"], [31, "N"]]], 0, 37, 23]], [[274, 93, [], [[[37, "W"], [36, "W"], [35, "N"], [27, "N"]]], 0, 37, 19]], [[275, 93, [], [[[37, "W"], [36, "W"], [35, "S"], [43, "S"]]], 0, 37, 51]]], "end_time": 0, "visited": 0, "total_needSend": 744, "exe_time": 10, "mapto": 37}, "267": {"total_needReceive": 744, "input_links": [], "start_time": 0, "out_links": [[[276, 93, [], [[[26, "S"], [34, "S"], [42, "E"], [43, "E"]]], 0, 26, 44]]], "end_time": 0, "visited": 0, "total_needSend": 93, "exe_time": 208, "mapto": 26}, "268": {"total_needReceive": 93, "input_links": [], "start_time": 0, "out_links": [[[267, 93, [], [[[55, "N"], [47, "N"], [39, "N"], [31, "W"], [30, "W"], [29, "W"], [28, "W"], [27, "W"]]], 0, 55, 26]]], "end_time": 0, "visited": 0, "total_needSend": 93, "exe_time": 161, "mapto": 55}, "269": {"total_needReceive": 93, "input_links": [], "start_time": 0, "out_links": [[[267, 93, [], [[[23, "W"], [22, "S"], [30, "W"], [29, "W"], [28, "W"], [27, "W"]]], 0, 23, 26]]], "end_time": 0, "visited": 0, "total_needSend": 93, "exe_time": 6, "mapto": 23}, "270": {"total_needReceive": 93, "input_links": [], "start_time": 0, "out_links": [[[267, 93, [], [[[19, "S"], [27, "W"]]], 0, 19, 26]]], "end_time": 0, "visited": 0, "total_needSend": 93, "exe_time": 4, "mapto": 19}, "271": {"total_needReceive": 93, "input_links": [], "start_time": 0, "out_links": [[[267, 93, [], [[[51, "W"], [50, "N"], [42, "N"], [34, "N"]]], 0, 51, 26]]], "end_time": 0, "visited": 0, "total_needSend": 93, "exe_time": 127, "mapto": 51}, "272": {"total_needReceive": 93, "input_links": [], "start_time": 0, "out_links": [[[267, 93, [], [[[55, "N"], [47, "N"], [39, "N"], [31, "W"], [30, "W"], [29, "W"], [28, "W"], [27, "W"]]], 0, 55, 26]]], "end_time": 0, "visited": 0, "total_needSend": 93, "exe_time": 82, "mapto": 55}, "273": {"total_needReceive": 93, "input_links": [], "start_time": 0, "out_links": [[[267, 93, [], [[[23, "S"], [31, "W"], [30, "W"], [29, "W"], [28, "W"], [27, "W"]]], 0, 23, 26]]], "end_time": 0, "visited": 0, "total_needSend": 93, "exe_time": 143, "mapto": 23}, "274": {"total_needReceive": 93, "input_links": [], "start_time": 0, "out_links": [[[267, 93, [], [[[19, "W"], [18, "S"]]], 0, 19, 26]]], "end_time": 0, "visited": 0, "total_needSend": 93, "exe_time": 29, "mapto": 19}, "275": {"total_needReceive": 93, "input_links": [], "start_time": 0, "out_links": [[[267, 93, [], [[[51, "W"], [50, "N"], [42, "N"], [34, "N"]]], 0, 51, 26]]], "end_time": 0, "visited": 0, "total_needSend": 93, "exe_time": 29, "mapto": 51}, "276": {"total_needReceive": 93, "input_links": [], "start_time": 0, "out_links": [[[289, 1, [], [[[44, "N"], [36, "E"]]], 0, 44, 37]]], "end_time": 0, "visited": 0, "total_needSend": 1, "exe_time": 91, "mapto": 44}, "277": {"total_needReceive": 1, "input_links": [], "start_time": 0, "out_links": [[[278, 93, [], [[[56, "N"], [48, "E"], [49, "N"], [41, "N"], [33, "N"], [25, "E"]]], 0, 56, 26]]], "end_time": 0, "visited": 0, "total_needSend": 93, "exe_time": 55, "mapto": 56}, "278": {"total_needReceive": 93, "input_links": [], "start_time": 0, "out_links": [[[280, 93, [], [[[26, "E"], [27, "E"], [28, "S"], [36, "S"]]], 0, 26, 44]], [[281, 93, [], [[[26, "E"], [27, "N"], [19, "N"], [11, "E"]]], 0, 26, 12]], [[282, 93, [], [[[26, "N"], [18, "N"], [10, "W"], [9, "W"]]], 0, 26, 8]], [[283, 93, [], [[[26, "S"], [34, "S"], [42, "W"], [41, "W"]]], 0, 26, 40]], [[284, 93, [], [[[26, "E"], [27, "E"], [28, "S"], [36, "S"]]], 0, 26, 44]], [[285, 93, [], [[[26, "N"], [18, "N"], [10, "E"], [11, "E"]]], 0, 26, 12]], [[286, 93, [], [[[26, "N"], [18, "N"], [10, "W"], [9, "W"]]], 0, 26, 8]], [[287, 93, [], [[[26, "S"], [34, "W"], [33, "W"], [32, "S"]]], 0, 26, 40]]], "end_time": 0, "visited": 0, "total_needSend": 744, "exe_time": 16, "mapto": 26}, "279": {"total_needReceive": 744, "input_links": [], "start_time": 0, "out_links": [[[288, 93, [], [[[19, "E"], [20, "E"], [21, "S"], [29, "S"]]], 0, 19, 37]]], "end_time": 0, "visited": 0, "total_needSend": 93, "exe_time": 429, "mapto": 19}, "280": {"total_needReceive": 93, "input_links": [], "start_time": 0, "out_links": [[[279, 93, [], [[[44, "W"], [43, "N"], [35, "N"], [27, "N"]]], 0, 44, 19]]], "end_time": 0, "visited": 0, "total_needSend": 93, "exe_time": 37, "mapto": 44}, "281": {"total_needReceive": 93, "input_links": [], "start_time": 0, "out_links": [[[279, 93, [], [[[12, "W"], [11, "S"]]], 0, 12, 19]]], "end_time": 0, "visited": 0, "total_needSend": 93, "exe_time": 12, "mapto": 12}, "282": {"total_needReceive": 93, "input_links": [], "start_time": 0, "out_links": [[[279, 93, [], [[[8, "E"], [9, "E"], [10, "E"], [11, "S"]]], 0, 8, 19]]], "end_time": 0, "visited": 0, "total_needSend": 93, "exe_time": 5, "mapto": 8}, "283": {"total_needReceive": 93, "input_links": [], "start_time": 0, "out_links": [[[279, 93, [], [[[40, "N"], [32, "N"], [24, "N"], [16, "E"], [17, "E"], [18, "E"]]], 0, 40, 19]]], "end_time": 0, "visited": 0, "total_needSend": 93, "exe_time": 73, "mapto": 40}, "284": {"total_needReceive": 93, "input_links": [], "start_time": 0, "out_links": [[[279, 93, [], [[[44, "W"], [43, "N"], [35, "N"], [27, "N"]]], 0, 44, 19]]], "end_time": 0, "visited": 0, "total_needSend": 93, "exe_time": 146, "mapto": 44}, "285": {"total_needReceive": 93, "input_links": [], "start_time": 0, "out_links": [[[279, 93, [], [[[12, "W"], [11, "S"]]], 0, 12, 19]]], "end_time": 0, "visited": 0, "total_needSend": 93, "exe_time": 19, "mapto": 12}, "286": {"total_needReceive": 93, "input_links": [], "start_time": 0, "out_links": [[[279, 93, [], [[[8, "E"], [9, "E"], [10, "E"], [11, "S"]]], 0, 8, 19]]], "end_time": 0, "visited": 0, "total_needSend": 93, "exe_time": 121, "mapto": 8}, "287": {"total_needReceive": 93, "input_links": [], "start_time": 0, "out_links": [[[279, 93, [], [[[40, "N"], [32, "N"], [24, "N"], [16, "E"], [17, "E"], [18, "E"]]], 0, 40, 19]]], "end_time": 0, "visited": 0, "total_needSend": 93, "exe_time": 135, "mapto": 40}, "288": {"total_needReceive": 93, "input_links": [], "start_time": 0, "out_links": [[[289, 1, [], [[]], 0, 37, 37]]], "end_time": 0, "visited": 0, "total_needSend": 1, "exe_time": 16, "mapto": 37}, "289": {"total_needReceive": 24, "input_links": [], "start_time": 0, "out_links": [], "end_time": 0, "visited": 0, "total_needSend": 0, "exe_time": 47, "mapto": 37}}